{
"meta":{"test_sets":[],"test_metrics":[],"learn_metrics":[{"best_value":"Min","name":"RMSE"}],"launch_mode":"Train","parameters":"","iteration_count":1000,"learn_sets":["learn"],"name":"experiment"},
"iterations":[
{"learn":[14.59871775],"iteration":0,"passed_time":0.1672131225,"remaining_time":167.0459093},
{"learn":[14.22518863],"iteration":1,"passed_time":0.1679853069,"remaining_time":83.82466815},
{"learn":[13.8866124],"iteration":2,"passed_time":0.168685789,"remaining_time":56.05991055},
{"learn":[13.52356875],"iteration":3,"passed_time":0.1693103557,"remaining_time":42.15827858},
{"learn":[13.18870211],"iteration":4,"passed_time":0.1699252845,"remaining_time":33.81513162},
{"learn":[12.9124226],"iteration":5,"passed_time":0.1711135125,"remaining_time":28.34780524},
{"learn":[12.60003351],"iteration":6,"passed_time":0.1721052794,"remaining_time":24.41436321},
{"learn":[12.32990573],"iteration":7,"passed_time":0.1730904162,"remaining_time":21.46321161},
{"learn":[12.0660619],"iteration":8,"passed_time":0.1738575143,"remaining_time":19.14364407},
{"learn":[11.77309809],"iteration":9,"passed_time":0.1745617421,"remaining_time":17.28161247},
{"learn":[11.49227636],"iteration":10,"passed_time":0.1752887466,"remaining_time":15.76005186},
{"learn":[11.26264833],"iteration":11,"passed_time":0.1761098171,"remaining_time":14.49970827},
{"learn":[11.04260393],"iteration":12,"passed_time":0.1774277258,"remaining_time":13.47085887},
{"learn":[10.79916926],"iteration":13,"passed_time":0.1781759557,"remaining_time":12.54867802},
{"learn":[10.5541002],"iteration":14,"passed_time":0.1789489874,"remaining_time":11.7509835},
{"learn":[10.31918115],"iteration":15,"passed_time":0.1795926516,"remaining_time":11.04494807},
{"learn":[10.10004441],"iteration":16,"passed_time":0.1803071428,"remaining_time":10.42599538},
{"learn":[9.894556723],"iteration":17,"passed_time":0.1809516725,"remaining_time":9.871919025},
{"learn":[9.690174082],"iteration":18,"passed_time":0.1816219167,"remaining_time":9.377426332},
{"learn":[9.506034866],"iteration":19,"passed_time":0.1823479896,"remaining_time":8.935051488},
{"learn":[9.338524633],"iteration":20,"passed_time":0.1831036737,"remaining_time":8.536118882},
{"learn":[9.170203312],"iteration":21,"passed_time":0.183813992,"remaining_time":8.171367462},
{"learn":[9.010299969],"iteration":22,"passed_time":0.1844891069,"remaining_time":7.83677641},
{"learn":[8.843866678],"iteration":23,"passed_time":0.1851465108,"remaining_time":7.52929144},
{"learn":[8.690548059],"iteration":24,"passed_time":0.1866989805,"remaining_time":7.281260239},
{"learn":[8.555307687],"iteration":25,"passed_time":0.1877281817,"remaining_time":7.0325865},
{"learn":[8.413851302],"iteration":26,"passed_time":0.1886072599,"remaining_time":6.796846812},
{"learn":[8.29256019],"iteration":27,"passed_time":0.1893168937,"remaining_time":6.572000738},
{"learn":[8.162193833],"iteration":28,"passed_time":0.1903234139,"remaining_time":6.372552927},
{"learn":[8.040736294],"iteration":29,"passed_time":0.1910659312,"remaining_time":6.177798442},
{"learn":[7.921220278],"iteration":30,"passed_time":0.1917623335,"remaining_time":5.994119393},
{"learn":[7.809589039],"iteration":31,"passed_time":0.1925325839,"remaining_time":5.824110662},
{"learn":[7.699675801],"iteration":32,"passed_time":0.193277366,"remaining_time":5.663612512},
{"learn":[7.60645267],"iteration":33,"passed_time":0.1939908854,"remaining_time":5.51162339},
{"learn":[7.498880302],"iteration":34,"passed_time":0.1947141925,"remaining_time":5.368548452},
{"learn":[7.401158744],"iteration":35,"passed_time":0.1955234036,"remaining_time":5.235682253},
{"learn":[7.306431077],"iteration":36,"passed_time":0.1961876198,"remaining_time":5.106180484},
{"learn":[7.223863468],"iteration":37,"passed_time":0.1969343622,"remaining_time":4.985548853},
{"learn":[7.143477682],"iteration":38,"passed_time":0.1976884275,"remaining_time":4.871245612},
{"learn":[7.062817131],"iteration":39,"passed_time":0.1985102215,"remaining_time":4.764245315},
{"learn":[6.990793435],"iteration":40,"passed_time":0.1992780774,"remaining_time":4.661162835},
{"learn":[6.931862224],"iteration":41,"passed_time":0.2000796252,"remaining_time":4.563720975},
{"learn":[6.858296558],"iteration":42,"passed_time":0.2011557224,"remaining_time":4.476884334},
{"learn":[6.786268161],"iteration":43,"passed_time":0.2026280421,"remaining_time":4.402554734},
{"learn":[6.717118549],"iteration":44,"passed_time":0.2036918976,"remaining_time":4.322794715},
{"learn":[6.652948106],"iteration":45,"passed_time":0.2050970951,"remaining_time":4.253535407},
{"learn":[6.589686076],"iteration":46,"passed_time":0.2060282285,"remaining_time":4.177551101},
{"learn":[6.531283097],"iteration":47,"passed_time":0.206751998,"remaining_time":4.100581294},
{"learn":[6.471368031],"iteration":48,"passed_time":0.2074512546,"remaining_time":4.026247818},
{"learn":[6.416481395],"iteration":49,"passed_time":0.208135375,"remaining_time":3.954572125},
{"learn":[6.369870822],"iteration":50,"passed_time":0.2088611912,"remaining_time":3.886456283},
{"learn":[6.325678067],"iteration":51,"passed_time":0.2094970742,"remaining_time":3.819292815},
{"learn":[6.275766122],"iteration":52,"passed_time":0.2102142814,"remaining_time":3.756092915},
{"learn":[6.224773967],"iteration":53,"passed_time":0.2109583997,"remaining_time":3.695678631},
{"learn":[6.182249254],"iteration":54,"passed_time":0.211707579,"remaining_time":3.63752113},
{"learn":[6.139904173],"iteration":55,"passed_time":0.2124638939,"remaining_time":3.581534211},
{"learn":[6.100525536],"iteration":56,"passed_time":0.2132164866,"remaining_time":3.52742363},
{"learn":[6.062568564],"iteration":57,"passed_time":0.2139865288,"remaining_time":3.475436381},
{"learn":[6.030559288],"iteration":58,"passed_time":0.2147533537,"remaining_time":3.425133997},
{"learn":[5.997931376],"iteration":59,"passed_time":0.2154602876,"remaining_time":3.375544506},
{"learn":[5.964103835],"iteration":60,"passed_time":0.2165405949,"remaining_time":3.333305224},
{"learn":[5.933729724],"iteration":61,"passed_time":0.2175531998,"remaining_time":3.291369378},
{"learn":[5.901932711],"iteration":62,"passed_time":0.2188245785,"remaining_time":3.254581429},
{"learn":[5.873727795],"iteration":63,"passed_time":0.2196695828,"remaining_time":3.212667648},
{"learn":[5.846485734],"iteration":64,"passed_time":0.2203786793,"remaining_time":3.170062541},
{"learn":[5.820630862],"iteration":65,"passed_time":0.2212887839,"remaining_time":3.131571579},
{"learn":[5.793646238],"iteration":66,"passed_time":0.2219871779,"remaining_time":3.091254284},
{"learn":[5.765388646],"iteration":67,"passed_time":0.2226343127,"remaining_time":3.051399698},
{"learn":[5.747073912],"iteration":68,"passed_time":0.223468605,"remaining_time":3.01520683},
{"learn":[5.722315217],"iteration":69,"passed_time":0.2242030919,"remaining_time":2.978698221},
{"learn":[5.699970599],"iteration":70,"passed_time":0.2249418084,"remaining_time":2.943252676},
{"learn":[5.682732647],"iteration":71,"passed_time":0.2256666913,"remaining_time":2.90859291},
{"learn":[5.663525791],"iteration":72,"passed_time":0.2264594153,"remaining_time":2.875724355},
{"learn":[5.642381613],"iteration":73,"passed_time":0.2272996358,"remaining_time":2.844317064},
{"learn":[5.621404779],"iteration":74,"passed_time":0.2280353879,"remaining_time":2.812436451},
{"learn":[5.602460129],"iteration":75,"passed_time":0.2287822321,"remaining_time":2.781510295},
{"learn":[5.587337574],"iteration":76,"passed_time":0.2295349465,"remaining_time":2.751438385},
{"learn":[5.572393026],"iteration":77,"passed_time":0.2301769953,"remaining_time":2.720810124},
{"learn":[5.558425806],"iteration":78,"passed_time":0.2322430512,"remaining_time":2.707542407},
{"learn":[5.541518902],"iteration":79,"passed_time":0.2334328652,"remaining_time":2.68447795},
{"learn":[5.526157283],"iteration":80,"passed_time":0.2348215611,"remaining_time":2.664210058},
{"learn":[5.511746977],"iteration":81,"passed_time":0.2360809468,"remaining_time":2.64295499},
{"learn":[5.504975022],"iteration":82,"passed_time":0.2365695262,"remaining_time":2.61366573},
{"learn":[5.493980522],"iteration":83,"passed_time":0.2375430106,"remaining_time":2.590349973},
{"learn":[5.480745463],"iteration":84,"passed_time":0.2412597716,"remaining_time":2.597090482},
{"learn":[5.464052013],"iteration":85,"passed_time":0.2421514003,"remaining_time":2.573562557},
{"learn":[5.449143727],"iteration":86,"passed_time":0.2430107291,"remaining_time":2.550216043},
{"learn":[5.438255432],"iteration":87,"passed_time":0.2438971242,"remaining_time":2.527661105},
{"learn":[5.425927931],"iteration":88,"passed_time":0.2447141678,"remaining_time":2.504883224},
{"learn":[5.412331217],"iteration":89,"passed_time":0.2454839314,"remaining_time":2.482115307},
{"learn":[5.400691499],"iteration":90,"passed_time":0.2463136005,"remaining_time":2.460429262},
{"learn":[5.391618744],"iteration":91,"passed_time":0.2484130593,"remaining_time":2.45172889},
{"learn":[5.380766572],"iteration":92,"passed_time":0.2494092611,"remaining_time":2.432410751},
{"learn":[5.372207183],"iteration":93,"passed_time":0.2501916767,"remaining_time":2.411421905},
{"learn":[5.362918837],"iteration":94,"passed_time":0.251557221,"remaining_time":2.396413526},
{"learn":[5.348292324],"iteration":95,"passed_time":0.2523060684,"remaining_time":2.375882144},
{"learn":[5.339772295],"iteration":96,"passed_time":0.2529700971,"remaining_time":2.354969048},
{"learn":[5.331515983],"iteration":97,"passed_time":0.2535968695,"remaining_time":2.334126288},
{"learn":[5.323861644],"iteration":98,"passed_time":0.2543228334,"remaining_time":2.314594676},
{"learn":[5.313277281],"iteration":99,"passed_time":0.2550985161,"remaining_time":2.295886645},
{"learn":[5.30685627],"iteration":100,"passed_time":0.2558833198,"remaining_time":2.277614896},
{"learn":[5.29652059],"iteration":101,"passed_time":0.2566393003,"remaining_time":2.259432271},
{"learn":[5.288350766],"iteration":102,"passed_time":0.2573637623,"remaining_time":2.241313541},
{"learn":[5.27993346],"iteration":103,"passed_time":0.2580985484,"remaining_time":2.223618263},
{"learn":[5.271789139],"iteration":104,"passed_time":0.2588645633,"remaining_time":2.20651223},
{"learn":[5.262684686],"iteration":105,"passed_time":0.2596873924,"remaining_time":2.190193668},
{"learn":[5.251619772],"iteration":106,"passed_time":0.2606106531,"remaining_time":2.175002927},
{"learn":[5.241012171],"iteration":107,"passed_time":0.2623289498,"remaining_time":2.166642807},
{"learn":[5.232684032],"iteration":108,"passed_time":0.2632830262,"remaining_time":2.152157581},
{"learn":[5.224267141],"iteration":109,"passed_time":0.2644683163,"remaining_time":2.139789105},
{"learn":[5.216324968],"iteration":110,"passed_time":0.2652208805,"remaining_time":2.124156421},
{"learn":[5.211102527],"iteration":111,"passed_time":0.2658888379,"remaining_time":2.108118643},
{"learn":[5.206364257],"iteration":112,"passed_time":0.2667691529,"remaining_time":2.09401981},
{"learn":[5.196937641],"iteration":113,"passed_time":0.2676125322,"remaining_time":2.079865821},
{"learn":[5.190746047],"iteration":114,"passed_time":0.2683357256,"remaining_time":2.06501841},
{"learn":[5.181885213],"iteration":115,"passed_time":0.269067451,"remaining_time":2.05047954},
{"learn":[5.178293568],"iteration":116,"passed_time":0.2695860751,"remaining_time":2.034568413},
{"learn":[5.170991438],"iteration":117,"passed_time":0.2703397687,"remaining_time":2.020675221},
{"learn":[5.166257212],"iteration":118,"passed_time":0.2711283455,"remaining_time":2.007261113},
{"learn":[5.161421246],"iteration":119,"passed_time":0.2718484388,"remaining_time":1.993555218},
{"learn":[5.158223542],"iteration":120,"passed_time":0.2725626527,"remaining_time":1.980021254},
{"learn":[5.15470988],"iteration":121,"passed_time":0.273091392,"remaining_time":1.965362641},
{"learn":[5.146388143],"iteration":122,"passed_time":0.2737837853,"remaining_time":1.952100648},
{"learn":[5.139529364],"iteration":123,"passed_time":0.2744433655,"remaining_time":1.938809582},
{"learn":[5.134276023],"iteration":124,"passed_time":0.2751126222,"remaining_time":1.925788355},
{"learn":[5.128536065],"iteration":125,"passed_time":0.2758537214,"remaining_time":1.913461528},
{"learn":[5.123300353],"iteration":126,"passed_time":0.2766713193,"remaining_time":1.901843006},
{"learn":[5.116200518],"iteration":127,"passed_time":0.2780007095,"remaining_time":1.893879833},
{"learn":[5.108728704],"iteration":128,"passed_time":0.2789319438,"remaining_time":1.883331187},
{"learn":[5.104075866],"iteration":129,"passed_time":0.2797547882,"remaining_time":1.872205121},
{"learn":[5.100317606],"iteration":130,"passed_time":0.2804729681,"remaining_time":1.860542055},
{"learn":[5.095814182],"iteration":131,"passed_time":0.2812754149,"remaining_time":1.84959894},
{"learn":[5.092146915],"iteration":132,"passed_time":0.2819702125,"remaining_time":1.838106573},
{"learn":[5.085258329],"iteration":133,"passed_time":0.2827164449,"remaining_time":1.827107771},
{"learn":[5.079219421],"iteration":134,"passed_time":0.2833518334,"remaining_time":1.815550636},
{"learn":[5.076476829],"iteration":135,"passed_time":0.2840697293,"remaining_time":1.80467828},
{"learn":[5.072133867],"iteration":136,"passed_time":0.284751286,"remaining_time":1.793725254},
{"learn":[5.067031564],"iteration":137,"passed_time":0.285492161,"remaining_time":1.783291614},
{"learn":[5.061358312],"iteration":138,"passed_time":0.2862014512,"remaining_time":1.772801795},
{"learn":[5.056759124],"iteration":139,"passed_time":0.2869106512,"remaining_time":1.762451143},
{"learn":[5.050254],"iteration":140,"passed_time":0.2875921599,"remaining_time":1.752068549},
{"learn":[5.048376474],"iteration":141,"passed_time":0.2880747926,"remaining_time":1.74062093},
{"learn":[5.042603751],"iteration":142,"passed_time":0.2888056587,"remaining_time":1.730814332},
{"learn":[5.037477349],"iteration":143,"passed_time":0.2897937122,"remaining_time":1.722662622},
{"learn":[5.03230489],"iteration":144,"passed_time":0.2906222033,"remaining_time":1.713668854},
{"learn":[5.025976187],"iteration":145,"passed_time":0.2920528305,"remaining_time":1.708309023},
{"learn":[5.01952451],"iteration":146,"passed_time":0.2934448766,"remaining_time":1.702778774},
{"learn":[5.017569424],"iteration":147,"passed_time":0.2944631071,"remaining_time":1.695152482},
{"learn":[5.008962367],"iteration":148,"passed_time":0.2952486235,"remaining_time":1.686285763},
{"learn":[5.003880266],"iteration":149,"passed_time":0.2959981158,"remaining_time":1.677322656},
{"learn":[4.996387564],"iteration":150,"passed_time":0.2968399199,"remaining_time":1.668987364},
{"learn":[4.993361683],"iteration":151,"passed_time":0.297557555,"remaining_time":1.660057939},
{"learn":[4.99005752],"iteration":152,"passed_time":0.2982625531,"remaining_time":1.651165899},
{"learn":[4.986908764],"iteration":153,"passed_time":0.2989385467,"remaining_time":1.642220848},
{"learn":[4.985207175],"iteration":154,"passed_time":0.2995775845,"remaining_time":1.633181025},
{"learn":[4.979003494],"iteration":155,"passed_time":0.3002928451,"remaining_time":1.62466129},
{"learn":[4.973142217],"iteration":156,"passed_time":0.3009406111,"remaining_time":1.615878568},
{"learn":[4.967056696],"iteration":157,"passed_time":0.3016100155,"remaining_time":1.607314133},
{"learn":[4.961460696],"iteration":158,"passed_time":0.3023660518,"remaining_time":1.59930723},
{"learn":[4.954240363],"iteration":159,"passed_time":0.3030684093,"remaining_time":1.591109149},
{"learn":[4.952320707],"iteration":160,"passed_time":0.303494669,"remaining_time":1.581565387},
{"learn":[4.948337777],"iteration":161,"passed_time":0.3041477788,"remaining_time":1.573307646},
{"learn":[4.943228639],"iteration":162,"passed_time":0.3048424456,"remaining_time":1.565356607},
{"learn":[4.938545759],"iteration":163,"passed_time":0.3055989294,"remaining_time":1.557809177},
{"learn":[4.935330572],"iteration":164,"passed_time":0.3065375369,"remaining_time":1.551265717},
{"learn":[4.932051543],"iteration":165,"passed_time":0.3077449928,"remaining_time":1.546140506},
{"learn":[4.928964153],"iteration":166,"passed_time":0.3087330814,"remaining_time":1.539968005},
{"learn":[4.922860227],"iteration":167,"passed_time":0.3095994862,"remaining_time":1.533254598},
{"learn":[4.917668772],"iteration":168,"passed_time":0.3103570452,"remaining_time":1.526075175},
{"learn":[4.910365386],"iteration":169,"passed_time":0.3110546193,"remaining_time":1.518678436},
{"learn":[4.906457206],"iteration":170,"passed_time":0.3117005948,"remaining_time":1.511109901},
{"learn":[4.901996508],"iteration":171,"passed_time":0.3123922783,"remaining_time":1.503841898},
{"learn":[4.896816173],"iteration":172,"passed_time":0.3130451815,"remaining_time":1.496464538},
{"learn":[4.891123132],"iteration":173,"passed_time":0.3137689084,"remaining_time":1.48950068},
{"learn":[4.887630202],"iteration":174,"passed_time":0.3144403396,"remaining_time":1.482361601},
{"learn":[4.885259712],"iteration":175,"passed_time":0.31511327,"remaining_time":1.475303037},
{"learn":[4.880659728],"iteration":176,"passed_time":0.3163810751,"remaining_time":1.471082626},
{"learn":[4.877299723],"iteration":177,"passed_time":0.3173159733,"remaining_time":1.465358034},
{"learn":[4.874038772],"iteration":178,"passed_time":0.3183170408,"remaining_time":1.45999045},
{"learn":[4.86943698],"iteration":179,"passed_time":0.3192723241,"remaining_time":1.45446281},
{"learn":[4.861268711],"iteration":180,"passed_time":0.3202351048,"remaining_time":1.449019618},
{"learn":[4.858673056],"iteration":181,"passed_time":0.3210974827,"remaining_time":1.4431744},
{"learn":[4.854036207],"iteration":182,"passed_time":0.3234573361,"remaining_time":1.444069091},
{"learn":[4.85130244],"iteration":183,"passed_time":0.3244556132,"remaining_time":1.438890111},
{"learn":[4.847510084],"iteration":184,"passed_time":0.3252980332,"remaining_time":1.433069714},
{"learn":[4.845691673],"iteration":185,"passed_time":0.3260622907,"remaining_time":1.426960778},
{"learn":[4.842058646],"iteration":186,"passed_time":0.326721034,"remaining_time":1.420450271},
{"learn":[4.838623675],"iteration":187,"passed_time":0.3274310506,"remaining_time":1.414223474},
{"learn":[4.834602161],"iteration":188,"passed_time":0.3282389314,"remaining_time":1.408474991},
{"learn":[4.830858976],"iteration":189,"passed_time":0.3289751691,"remaining_time":1.402473089},
{"learn":[4.827590511],"iteration":190,"passed_time":0.329826417,"remaining_time":1.397013463},
{"learn":[4.822246226],"iteration":191,"passed_time":0.3305430526,"remaining_time":1.391035346},
{"learn":[4.816686395],"iteration":192,"passed_time":0.3312503963,"remaining_time":1.3850729},
{"learn":[4.814797121],"iteration":193,"passed_time":0.3319777667,"remaining_time":1.379247835},
{"learn":[4.811639392],"iteration":194,"passed_time":0.3326335808,"remaining_time":1.373179654},
{"learn":[4.804813432],"iteration":195,"passed_time":0.3333711206,"remaining_time":1.367501944},
{"learn":[4.80251613],"iteration":196,"passed_time":0.3340457367,"remaining_time":1.361617902},
{"learn":[4.800087884],"iteration":197,"passed_time":0.3348043649,"remaining_time":1.356126771},
{"learn":[4.794773135],"iteration":198,"passed_time":0.3355271651,"remaining_time":1.350538991},
{"learn":[4.791664833],"iteration":199,"passed_time":0.3362693926,"remaining_time":1.34507757},
{"learn":[4.785989873],"iteration":200,"passed_time":0.3374281976,"remaining_time":1.341319054},
{"learn":[4.782387142],"iteration":201,"passed_time":0.3388854197,"remaining_time":1.338765173},
{"learn":[4.778623704],"iteration":202,"passed_time":0.339750442,"remaining_time":1.333897056},
{"learn":[4.775772178],"iteration":203,"passed_time":0.3404277688,"remaining_time":1.328335804},
{"learn":[4.77023101],"iteration":204,"passed_time":0.341195388,"remaining_time":1.323172358},
{"learn":[4.764496689],"iteration":205,"passed_time":0.3420697197,"remaining_time":1.3184629},
{"learn":[4.763138716],"iteration":206,"passed_time":0.3427235364,"remaining_time":1.312945721},
{"learn":[4.758053283],"iteration":207,"passed_time":0.343464331,"remaining_time":1.307806491},
{"learn":[4.755063788],"iteration":208,"passed_time":0.3442984983,"remaining_time":1.303062738},
{"learn":[4.752465267],"iteration":209,"passed_time":0.3450515976,"remaining_time":1.298051248},
{"learn":[4.748067377],"iteration":210,"passed_time":0.3458348728,"remaining_time":1.29319296},
{"learn":[4.744163298],"iteration":211,"passed_time":0.3465342225,"remaining_time":1.288061167},
{"learn":[4.736670896],"iteration":212,"passed_time":0.3473029249,"remaining_time":1.283227239},
{"learn":[4.73349255],"iteration":213,"passed_time":0.3480431268,"remaining_time":1.278326625},
{"learn":[4.731864595],"iteration":214,"passed_time":0.3488078078,"remaining_time":1.273554089},
{"learn":[4.728398311],"iteration":215,"passed_time":0.349574379,"remaining_time":1.268825524},
{"learn":[4.723865975],"iteration":216,"passed_time":0.3503444145,"remaining_time":1.264145975},
{"learn":[4.723483365],"iteration":217,"passed_time":0.3510530069,"remaining_time":1.259281887},
{"learn":[4.72095416],"iteration":218,"passed_time":0.3528995841,"remaining_time":1.258514042},
{"learn":[4.716173382],"iteration":219,"passed_time":0.3537946751,"remaining_time":1.254362939},
{"learn":[4.710563974],"iteration":220,"passed_time":0.3548275923,"remaining_time":1.250727124},
{"learn":[4.707160263],"iteration":221,"passed_time":0.3555632832,"remaining_time":1.246073128},
{"learn":[4.70408351],"iteration":222,"passed_time":0.3564302919,"remaining_time":1.241911824},
{"learn":[4.702501831],"iteration":223,"passed_time":0.3572939959,"remaining_time":1.237768486},
{"learn":[4.700269738],"iteration":224,"passed_time":0.3579402086,"remaining_time":1.232905163},
{"learn":[4.695346302],"iteration":225,"passed_time":0.3585987743,"remaining_time":1.228121466},
{"learn":[4.689769299],"iteration":226,"passed_time":0.3592411882,"remaining_time":1.223319112},
{"learn":[4.687919514],"iteration":227,"passed_time":0.3599196676,"remaining_time":1.218675366},
{"learn":[4.682982074],"iteration":228,"passed_time":0.3606158407,"remaining_time":1.214125822},
{"learn":[4.679578702],"iteration":229,"passed_time":0.3612545154,"remaining_time":1.209417291},
{"learn":[4.675751423],"iteration":230,"passed_time":0.3619193471,"remaining_time":1.204831073},
{"learn":[4.672710726],"iteration":231,"passed_time":0.3625755362,"remaining_time":1.200250051},
{"learn":[4.6690533],"iteration":232,"passed_time":0.363298449,"remaining_time":1.195922362},
{"learn":[4.667595702],"iteration":233,"passed_time":0.3639604318,"remaining_time":1.191426029},
{"learn":[4.664241291],"iteration":234,"passed_time":0.3646795049,"remaining_time":1.187148175},
{"learn":[4.662246999],"iteration":235,"passed_time":0.3654398436,"remaining_time":1.18303407},
{"learn":[4.658668443],"iteration":236,"passed_time":0.3661664707,"remaining_time":1.178839735},
{"learn":[4.658017572],"iteration":237,"passed_time":0.3670594562,"remaining_time":1.175207166},
{"learn":[4.657656705],"iteration":238,"passed_time":0.368416396,"remaining_time":1.173074801},
{"learn":[4.653242871],"iteration":239,"passed_time":0.3693820747,"remaining_time":1.169709903},
{"learn":[4.6507302],"iteration":240,"passed_time":0.3702375792,"remaining_time":1.166017936},
{"learn":[4.647671336],"iteration":241,"passed_time":0.3710444008,"remaining_time":1.162196925},
{"learn":[4.645506007],"iteration":242,"passed_time":0.3719073227,"remaining_time":1.158575487},
{"learn":[4.641297906],"iteration":243,"passed_time":0.3725778346,"remaining_time":1.154380504},
{"learn":[4.63798107],"iteration":244,"passed_time":0.3733125438,"remaining_time":1.150412125},
{"learn":[4.635062318],"iteration":245,"passed_time":0.374020113,"remaining_time":1.14638685},
{"learn":[4.631606017],"iteration":246,"passed_time":0.3746104858,"remaining_time":1.142031157},
{"learn":[4.630215494],"iteration":247,"passed_time":0.3752333821,"remaining_time":1.137804449},
{"learn":[4.62729814],"iteration":248,"passed_time":0.3759294533,"remaining_time":1.133827387},
{"learn":[4.624691756],"iteration":249,"passed_time":0.3766474821,"remaining_time":1.129942446},
{"learn":[4.621840053],"iteration":250,"passed_time":0.3773274106,"remaining_time":1.125969046},
{"learn":[4.619602091],"iteration":251,"passed_time":0.3779961358,"remaining_time":1.12198853},
{"learn":[4.613584029],"iteration":252,"passed_time":0.3786739008,"remaining_time":1.118060885},
{"learn":[4.6119388],"iteration":253,"passed_time":0.3794198348,"remaining_time":1.114359042},
{"learn":[4.60870702],"iteration":254,"passed_time":0.3801291784,"remaining_time":1.110573482},
{"learn":[4.604771557],"iteration":255,"passed_time":0.3808435893,"remaining_time":1.106826682},
{"learn":[4.604231277],"iteration":256,"passed_time":0.3815858508,"remaining_time":1.103183997},
{"learn":[4.600750354],"iteration":257,"passed_time":0.3830652771,"remaining_time":1.101683859},
{"learn":[4.596488253],"iteration":258,"passed_time":0.3848406073,"remaining_time":1.101030463},
{"learn":[4.59470784],"iteration":259,"passed_time":0.3861335627,"remaining_time":1.098995525},
{"learn":[4.588818005],"iteration":260,"passed_time":0.3872709148,"remaining_time":1.096525694},
{"learn":[4.585054174],"iteration":261,"passed_time":0.388249274,"remaining_time":1.093618184},
{"learn":[4.581471435],"iteration":262,"passed_time":0.3890225151,"remaining_time":1.090150546},
{"learn":[4.577555199],"iteration":263,"passed_time":0.3898195246,"remaining_time":1.086769584},
{"learn":[4.57457145],"iteration":264,"passed_time":0.3905419481,"remaining_time":1.083201252},
{"learn":[4.573029224],"iteration":265,"passed_time":0.3912394448,"remaining_time":1.079585536},
{"learn":[4.571326203],"iteration":266,"passed_time":0.3920067179,"remaining_time":1.076183237},
{"learn":[4.571019224],"iteration":267,"passed_time":0.3927521743,"remaining_time":1.072741013},
{"learn":[4.565766631],"iteration":268,"passed_time":0.3935404775,"remaining_time":1.069435275},
{"learn":[4.563383471],"iteration":269,"passed_time":0.3942130676,"remaining_time":1.065835331},
{"learn":[4.558165805],"iteration":270,"passed_time":0.3949854205,"remaining_time":1.062525356},
{"learn":[4.55629209],"iteration":271,"passed_time":0.3956980716,"remaining_time":1.05907425},
{"learn":[4.549383848],"iteration":272,"passed_time":0.3964294816,"remaining_time":1.055693162},
{"learn":[4.546227503],"iteration":273,"passed_time":0.3983013441,"remaining_time":1.055353196},
{"learn":[4.540620977],"iteration":274,"passed_time":0.4001144525,"remaining_time":1.054847193},
{"learn":[4.532898237],"iteration":275,"passed_time":0.4009758992,"remaining_time":1.05183533},
{"learn":[4.529757367],"iteration":276,"passed_time":0.4021508602,"remaining_time":1.049657299},
{"learn":[4.52579294],"iteration":277,"passed_time":0.4029945649,"remaining_time":1.046626172},
{"learn":[4.521572155],"iteration":278,"passed_time":0.4038120622,"remaining_time":1.043542999},
{"learn":[4.518818099],"iteration":279,"passed_time":0.4045645055,"remaining_time":1.040308728},
{"learn":[4.514012334],"iteration":280,"passed_time":0.4053197264,"remaining_time":1.037099229},
{"learn":[4.508331416],"iteration":281,"passed_time":0.4060122431,"remaining_time":1.033747484},
{"learn":[4.506038537],"iteration":282,"passed_time":0.4067976503,"remaining_time":1.030649877},
{"learn":[4.505805643],"iteration":283,"passed_time":0.4074530853,"remaining_time":1.027240877},
{"learn":[4.501550352],"iteration":284,"passed_time":0.4080908698,"remaining_time":1.023806919},
{"learn":[4.494692643],"iteration":285,"passed_time":0.4087124188,"remaining_time":1.020351983},
{"learn":[4.489330245],"iteration":286,"passed_time":0.4093811407,"remaining_time":1.017033984},
{"learn":[4.484826955],"iteration":287,"passed_time":0.4101269633,"remaining_time":1.013924993},
{"learn":[4.478285428],"iteration":288,"passed_time":0.4108824153,"remaining_time":1.010856046},
{"learn":[4.475311671],"iteration":289,"passed_time":0.4119106041,"remaining_time":1.008470789},
{"learn":[4.471581298],"iteration":290,"passed_time":0.4129973355,"remaining_time":1.006237494},
{"learn":[4.469164956],"iteration":291,"passed_time":0.4140625187,"remaining_time":1.003959806},
{"learn":[4.462068024],"iteration":292,"passed_time":0.4150726874,"remaining_time":1.001557645},
{"learn":[4.458540976],"iteration":293,"passed_time":0.4158997672,"remaining_time":0.9987252913},
{"learn":[4.455757458],"iteration":294,"passed_time":0.4167644369,"remaining_time":0.9959963661},
{"learn":[4.453027414],"iteration":295,"passed_time":0.4174328492,"remaining_time":0.9928132629},
{"learn":[4.450659338],"iteration":296,"passed_time":0.418103059,"remaining_time":0.9896513484},
{"learn":[4.444696901],"iteration":297,"passed_time":0.4188618726,"remaining_time":0.9867148811},
{"learn":[4.442052813],"iteration":298,"passed_time":0.4196279467,"remaining_time":0.9838100022},
{"learn":[4.440036756],"iteration":299,"passed_time":0.4203151974,"remaining_time":0.9807354607},
{"learn":[4.435017051],"iteration":300,"passed_time":0.4210861439,"remaining_time":0.9778711448},
{"learn":[4.429962125],"iteration":301,"passed_time":0.4217429171,"remaining_time":0.9747568083},
{"learn":[4.427666256],"iteration":302,"passed_time":0.422414936,"remaining_time":0.9716937637},
{"learn":[4.425030004],"iteration":303,"passed_time":0.4231278478,"remaining_time":0.9687400726},
{"learn":[4.422588771],"iteration":304,"passed_time":0.4238346762,"remaining_time":0.9657872129},
{"learn":[4.418936667],"iteration":305,"passed_time":0.4245472776,"remaining_time":0.9628621262},
{"learn":[4.416887976],"iteration":306,"passed_time":0.4252604865,"remaining_time":0.9599528246},
{"learn":[4.413773354],"iteration":307,"passed_time":0.426004505,"remaining_time":0.9571270048},
{"learn":[4.411129391],"iteration":308,"passed_time":0.4266508439,"remaining_time":0.9540962236},
{"learn":[4.40850819],"iteration":309,"passed_time":0.4278644991,"remaining_time":0.9523435624},
{"learn":[4.404880292],"iteration":310,"passed_time":0.4289453842,"remaining_time":0.9503002242},
{"learn":[4.404593827],"iteration":311,"passed_time":0.4297461374,"remaining_time":0.9476453285},
{"learn":[4.402139942],"iteration":312,"passed_time":0.430532571,"remaining_time":0.9449708507},
{"learn":[4.400284725],"iteration":313,"passed_time":0.4312716736,"remaining_time":0.942204994},
{"learn":[4.395805521],"iteration":314,"passed_time":0.4321716494,"remaining_time":0.9398018408},
{"learn":[4.392838833],"iteration":315,"passed_time":0.4329049244,"remaining_time":0.937047368},
{"learn":[4.389213061],"iteration":316,"passed_time":0.4335913093,"remaining_time":0.934204619},
{"learn":[4.3861981],"iteration":317,"passed_time":0.4343626092,"remaining_time":0.9315575456},
{"learn":[4.385054234],"iteration":318,"passed_time":0.435085546,"remaining_time":0.9288189868},
{"learn":[4.379364607],"iteration":319,"passed_time":0.435874273,"remaining_time":0.9262328301},
{"learn":[4.378387619],"iteration":320,"passed_time":0.436648024,"remaining_time":0.9236261941},
{"learn":[4.375816727],"iteration":321,"passed_time":0.4374236964,"remaining_time":0.921034988},
{"learn":[4.374600202],"iteration":322,"passed_time":0.4381658954,"remaining_time":0.9183848643},
{"learn":[4.37098897],"iteration":323,"passed_time":0.4394072112,"remaining_time":0.916787885},
{"learn":[4.367418484],"iteration":324,"passed_time":0.4401794606,"remaining_time":0.9142188797},
{"learn":[4.363584638],"iteration":325,"passed_time":0.4409151995,"remaining_time":0.9115854125},
{"learn":[4.360770706],"iteration":326,"passed_time":0.4416772696,"remaining_time":0.9090177446},
{"learn":[4.358675808],"iteration":327,"passed_time":0.442788343,"remaining_time":0.9071761175},
{"learn":[4.354228195],"iteration":328,"passed_time":0.443730318,"remaining_time":0.9049940528},
{"learn":[4.353773425],"iteration":329,"passed_time":0.4447132396,"remaining_time":0.9029026379},
{"learn":[4.351648009],"iteration":330,"passed_time":0.4456327653,"remaining_time":0.9006897884},
{"learn":[4.348209927],"iteration":331,"passed_time":0.4464516764,"remaining_time":0.8982822886},
{"learn":[4.345852733],"iteration":332,"passed_time":0.4472119941,"remaining_time":0.8957669671},
{"learn":[4.34237339],"iteration":333,"passed_time":0.4480078521,"remaining_time":0.8933330224},
{"learn":[4.340814362],"iteration":334,"passed_time":0.4487998406,"remaining_time":0.890901176},
{"learn":[4.339707068],"iteration":335,"passed_time":0.4495336491,"remaining_time":0.8883641161},
{"learn":[4.335430786],"iteration":336,"passed_time":0.4503131963,"remaining_time":0.8859277423},
{"learn":[4.33521887],"iteration":337,"passed_time":0.4510973403,"remaining_time":0.8835101753},
{"learn":[4.328507238],"iteration":338,"passed_time":0.4518945178,"remaining_time":0.8811276585},
{"learn":[4.326140732],"iteration":339,"passed_time":0.452613698,"remaining_time":0.8786030608},
{"learn":[4.323785636],"iteration":340,"passed_time":0.4538310435,"remaining_time":0.877051782},
{"learn":[4.320632534],"iteration":341,"passed_time":0.454663186,"remaining_time":0.8747613345},
{"learn":[4.31973724],"iteration":342,"passed_time":0.4555214553,"remaining_time":0.8725294347},
{"learn":[4.318000924],"iteration":343,"passed_time":0.4562189068,"remaining_time":0.8699988456},
{"learn":[4.312713628],"iteration":344,"passed_time":0.4598324159,"remaining_time":0.8730151664},
{"learn":[4.308220789],"iteration":345,"passed_time":0.460913801,"remaining_time":0.8712070112},
{"learn":[4.305890947],"iteration":346,"passed_time":0.4617479274,"remaining_time":0.8689377423},
{"learn":[4.305137856],"iteration":347,"passed_time":0.4625269382,"remaining_time":0.8665734589},
{"learn":[4.304787172],"iteration":348,"passed_time":0.4632209834,"remaining_time":0.8640597713},
{"learn":[4.30350134],"iteration":349,"passed_time":0.4640280965,"remaining_time":0.8617664648},
{"learn":[4.30293809],"iteration":350,"passed_time":0.4647925862,"remaining_time":0.8594028161},
{"learn":[4.299548459],"iteration":351,"passed_time":0.4654538716,"remaining_time":0.8568582637},
{"learn":[4.294768408],"iteration":352,"passed_time":0.4663192354,"remaining_time":0.8546984287},
{"learn":[4.294581479],"iteration":353,"passed_time":0.467031944,"remaining_time":0.8522673328},
{"learn":[4.292551604],"iteration":354,"passed_time":0.467959856,"remaining_time":0.8502369215},
{"learn":[4.288628894],"iteration":355,"passed_time":0.4686076034,"remaining_time":0.8477058892},
{"learn":[4.287802767],"iteration":356,"passed_time":0.4693608372,"remaining_time":0.8453754015},
{"learn":[4.284566905],"iteration":357,"passed_time":0.4700965281,"remaining_time":0.8430222655},
{"learn":[4.27890232],"iteration":358,"passed_time":0.4708126265,"remaining_time":0.8406431576},
{"learn":[4.276938023],"iteration":359,"passed_time":0.4715373517,"remaining_time":0.8382886252},
{"learn":[4.273425094],"iteration":360,"passed_time":0.473131965,"remaining_time":0.8374828964},
{"learn":[4.269726505],"iteration":361,"passed_time":0.474351387,"remaining_time":0.8360115605},
{"learn":[4.265565857],"iteration":362,"passed_time":0.4752262575,"remaining_time":0.8339369864},
{"learn":[4.262117173],"iteration":363,"passed_time":0.4760228076,"remaining_time":0.8317321583},
{"learn":[4.259185148],"iteration":364,"passed_time":0.4769727612,"remaining_time":0.829801927},
{"learn":[4.257668507],"iteration":365,"passed_time":0.4777028028,"remaining_time":0.827496112},
{"learn":[4.253432436],"iteration":366,"passed_time":0.4783858459,"remaining_time":0.8251178214},
{"learn":[4.250216667],"iteration":367,"passed_time":0.4791128806,"remaining_time":0.822824295},
{"learn":[4.24514828],"iteration":368,"passed_time":0.4797913183,"remaining_time":0.8204561567},
{"learn":[4.244015772],"iteration":369,"passed_time":0.4805110299,"remaining_time":0.8181674293},
{"learn":[4.240329192],"iteration":370,"passed_time":0.4814162936,"remaining_time":0.8162017485},
{"learn":[4.236718014],"iteration":371,"passed_time":0.4822532622,"remaining_time":0.8141264748},
{"learn":[4.233495944],"iteration":372,"passed_time":0.483024539,"remaining_time":0.8119474153},
{"learn":[4.230357491],"iteration":373,"passed_time":0.4837348776,"remaining_time":0.809673886},
{"learn":[4.227381215],"iteration":374,"passed_time":0.4844543968,"remaining_time":0.8074239946},
{"learn":[4.226169067],"iteration":375,"passed_time":0.485169431,"remaining_time":0.8051748004},
{"learn":[4.225963861],"iteration":376,"passed_time":0.4859263804,"remaining_time":0.8030030106},
{"learn":[4.224346548],"iteration":377,"passed_time":0.4866589924,"remaining_time":0.8007986594},
{"learn":[4.222595381],"iteration":378,"passed_time":0.4875428324,"remaining_time":0.7988498653},
{"learn":[4.219700938],"iteration":379,"passed_time":0.4885722282,"remaining_time":0.7971441618},
{"learn":[4.216356207],"iteration":380,"passed_time":0.4897562432,"remaining_time":0.795693214},
{"learn":[4.214326494],"iteration":381,"passed_time":0.4908143111,"remaining_time":0.7940399064},
{"learn":[4.212901398],"iteration":382,"passed_time":0.491724518,"remaining_time":0.792151508},
{"learn":[4.211331091],"iteration":383,"passed_time":0.4926257147,"remaining_time":0.7902537507},
{"learn":[4.208624791],"iteration":384,"passed_time":0.4933825859,"remaining_time":0.7881306242},
{"learn":[4.204659106],"iteration":385,"passed_time":0.4941894303,"remaining_time":0.7860940679},
{"learn":[4.202968852],"iteration":386,"passed_time":0.4949182382,"remaining_time":0.7839402584},
{"learn":[4.197261935],"iteration":387,"passed_time":0.4958024714,"remaining_time":0.7820389498},
{"learn":[4.196934403],"iteration":388,"passed_time":0.4964848287,"remaining_time":0.7798257849},
{"learn":[4.192479929],"iteration":389,"passed_time":0.49721835,"remaining_time":0.7777004961},
{"learn":[4.190243116],"iteration":390,"passed_time":0.4980312257,"remaining_time":0.7757059244},
{"learn":[4.185852431],"iteration":391,"passed_time":0.498771892,"remaining_time":0.7736053835},
{"learn":[4.180967944],"iteration":392,"passed_time":0.4995023112,"remaining_time":0.7714959361},
{"learn":[4.178283162],"iteration":393,"passed_time":0.5001665133,"remaining_time":0.7692916423},
{"learn":[4.176341157],"iteration":394,"passed_time":0.5008758759,"remaining_time":0.7671643163},
{"learn":[4.176041504],"iteration":395,"passed_time":0.5015620932,"remaining_time":0.7650088492},
{"learn":[4.175564513],"iteration":396,"passed_time":0.502396969,"remaining_time":0.7630865802},
{"learn":[4.170830274],"iteration":397,"passed_time":0.5036315053,"remaining_time":0.7617742869},
{"learn":[4.167804808],"iteration":398,"passed_time":0.5045375922,"remaining_time":0.7599676514},
{"learn":[4.165860548],"iteration":399,"passed_time":0.5054913586,"remaining_time":0.7582370379},
{"learn":[4.160950571],"iteration":400,"passed_time":0.5062694001,"remaining_time":0.7562478071},
{"learn":[4.158544115],"iteration":401,"passed_time":0.5072479592,"remaining_time":0.7545628846},
{"learn":[4.154448767],"iteration":402,"passed_time":0.5079858409,"remaining_time":0.7525249305},
{"learn":[4.15197457],"iteration":403,"passed_time":0.5089567835,"remaining_time":0.7508372351},
{"learn":[4.149562679],"iteration":404,"passed_time":0.5096733612,"remaining_time":0.7487793824},
{"learn":[4.149327961],"iteration":405,"passed_time":0.5102852552,"remaining_time":0.7465749794},
{"learn":[4.147444889],"iteration":406,"passed_time":0.510974248,"remaining_time":0.7444907349},
{"learn":[4.147254809],"iteration":407,"passed_time":0.5116584728,"remaining_time":0.7424064115},
{"learn":[4.144589165],"iteration":408,"passed_time":0.5123304508,"remaining_time":0.7403112381},
{"learn":[4.141691034],"iteration":409,"passed_time":0.5130286651,"remaining_time":0.738260762},
{"learn":[4.138893468],"iteration":410,"passed_time":0.5137068913,"remaining_time":0.7361882213},
{"learn":[4.136964597],"iteration":411,"passed_time":0.5143940969,"remaining_time":0.7341352645},
{"learn":[4.133773523],"iteration":412,"passed_time":0.5151178908,"remaining_time":0.7321409247},
{"learn":[4.131363444],"iteration":413,"passed_time":0.5158435642,"remaining_time":0.7301553832},
{"learn":[4.130228592],"iteration":414,"passed_time":0.5166082501,"remaining_time":0.7282309068},
{"learn":[4.12884186],"iteration":415,"passed_time":0.5172583728,"remaining_time":0.7261511772},
{"learn":[4.12413494],"iteration":416,"passed_time":0.5188539588,"remaining_time":0.725400139},
{"learn":[4.119422508],"iteration":417,"passed_time":0.5200039271,"remaining_time":0.7240246067},
{"learn":[4.117038244],"iteration":418,"passed_time":0.5209248812,"remaining_time":0.7223325918},
{"learn":[4.116067631],"iteration":419,"passed_time":0.5219811789,"remaining_time":0.7208311518},
{"learn":[4.110343455],"iteration":420,"passed_time":0.5228149745,"remaining_time":0.71902582},
{"learn":[4.105604544],"iteration":421,"passed_time":0.5234676795,"remaining_time":0.7169770586},
{"learn":[4.103390131],"iteration":422,"passed_time":0.5241961806,"remaining_time":0.7150382889},
{"learn":[4.096724402],"iteration":423,"passed_time":0.5249407115,"remaining_time":0.7131270043},
{"learn":[4.093431279],"iteration":424,"passed_time":0.5256418861,"remaining_time":0.7111625517},
{"learn":[4.091412744],"iteration":425,"passed_time":0.5263127801,"remaining_time":0.7091632295},
{"learn":[4.091192901],"iteration":426,"passed_time":0.5269035042,"remaining_time":0.7070625479},
{"learn":[4.088994581],"iteration":427,"passed_time":0.5275699679,"remaining_time":0.705070144},
{"learn":[4.087845355],"iteration":428,"passed_time":0.5282849943,"remaining_time":0.7031485588},
{"learn":[4.083650279],"iteration":429,"passed_time":0.528957269,"remaining_time":0.7011759148},
{"learn":[4.079840652],"iteration":430,"passed_time":0.5296956482,"remaining_time":0.699296575},
{"learn":[4.075707828],"iteration":431,"passed_time":0.5303520832,"remaining_time":0.6973147761},
{"learn":[4.071345409],"iteration":432,"passed_time":0.5310213328,"remaining_time":0.6953558792},
{"learn":[4.067460475],"iteration":433,"passed_time":0.5316802934,"remaining_time":0.693389507},
{"learn":[4.064914749],"iteration":434,"passed_time":0.5324272484,"remaining_time":0.6915434376},
{"learn":[4.063823175],"iteration":435,"passed_time":0.5334825193,"remaining_time":0.6901012405},
{"learn":[4.058898471],"iteration":436,"passed_time":0.5345324169,"remaining_time":0.6886538918},
{"learn":[4.054120355],"iteration":437,"passed_time":0.5354240639,"remaining_time":0.6870053057},
{"learn":[4.052715901],"iteration":438,"passed_time":0.5360775511,"remaining_time":0.6850558227},
{"learn":[4.052114167],"iteration":439,"passed_time":0.5368006443,"remaining_time":0.6832008201},
{"learn":[4.051377267],"iteration":440,"passed_time":0.5375952234,"remaining_time":0.6814415643},
{"learn":[4.049275336],"iteration":441,"passed_time":0.5382392138,"remaining_time":0.679496564},
{"learn":[4.047099198],"iteration":442,"passed_time":0.5389421838,"remaining_time":0.6776315946},
{"learn":[4.044348685],"iteration":443,"passed_time":0.5396479911,"remaining_time":0.6757754123},
{"learn":[4.042822379],"iteration":444,"passed_time":0.5403700732,"remaining_time":0.673944698},
{"learn":[4.041258611],"iteration":445,"passed_time":0.5410342687,"remaining_time":0.6720470512},
{"learn":[4.040044254],"iteration":446,"passed_time":0.5417015767,"remaining_time":0.6701587739},
{"learn":[4.036860137],"iteration":447,"passed_time":0.5427898507,"remaining_time":0.6687946375},
{"learn":[4.036372284],"iteration":448,"passed_time":0.5436438899,"remaining_time":0.6671442836},
{"learn":[4.03368231],"iteration":449,"passed_time":0.5445285504,"remaining_time":0.6655348949},
{"learn":[4.032439519],"iteration":450,"passed_time":0.5452495902,"remaining_time":0.6637295455},
{"learn":[4.032008634],"iteration":451,"passed_time":0.5459066837,"remaining_time":0.6618514661},
{"learn":[4.030034932],"iteration":452,"passed_time":0.5466137712,"remaining_time":0.6600391453},
{"learn":[4.028173412],"iteration":453,"passed_time":0.5473424151,"remaining_time":0.6582576182},
{"learn":[4.023806097],"iteration":454,"passed_time":0.5485267711,"remaining_time":0.657026572},
{"learn":[4.020239186],"iteration":455,"passed_time":0.5495748265,"remaining_time":0.6556331264},
{"learn":[4.017384838],"iteration":456,"passed_time":0.5507470446,"remaining_time":0.6543887204},
{"learn":[4.016468229],"iteration":457,"passed_time":0.5515765999,"remaining_time":0.6527391204},
{"learn":[4.014530169],"iteration":458,"passed_time":0.5524020787,"remaining_time":0.6510882888},
{"learn":[4.012884822],"iteration":459,"passed_time":0.5532131639,"remaining_time":0.6494241489},
{"learn":[4.008924707],"iteration":460,"passed_time":0.5539866861,"remaining_time":0.6477197913},
{"learn":[4.008286778],"iteration":461,"passed_time":0.5547466581,"remaining_time":0.6460036842},
{"learn":[4.006444202],"iteration":462,"passed_time":0.5555218123,"remaining_time":0.6443093158},
{"learn":[4.003284363],"iteration":463,"passed_time":0.5562520621,"remaining_time":0.6425670373},
{"learn":[3.999811484],"iteration":464,"passed_time":0.5569728648,"remaining_time":0.6408182423},
{"learn":[3.997483319],"iteration":465,"passed_time":0.5576776473,"remaining_time":0.6390555014},
{"learn":[3.99708333],"iteration":466,"passed_time":0.5583934191,"remaining_time":0.6373098338},
{"learn":[3.995860263],"iteration":467,"passed_time":0.5590839367,"remaining_time":0.6355398597},
{"learn":[3.994131111],"iteration":468,"passed_time":0.5597802021,"remaining_time":0.6337809964},
{"learn":[3.993125499],"iteration":469,"passed_time":0.5604269834,"remaining_time":0.6319708536},
{"learn":[3.992954084],"iteration":470,"passed_time":0.5610192406,"remaining_time":0.6301044125},
{"learn":[3.990635743],"iteration":471,"passed_time":0.5616821328,"remaining_time":0.6283223858},
{"learn":[3.986678254],"iteration":472,"passed_time":0.5624096443,"remaining_time":0.6266170879},
{"learn":[3.986393291],"iteration":473,"passed_time":0.5634100194,"remaining_time":0.6252187136},
{"learn":[3.986152671],"iteration":474,"passed_time":0.5649289417,"remaining_time":0.6243951461},
{"learn":[3.985596662],"iteration":475,"passed_time":0.5658732444,"remaining_time":0.6229360925},
{"learn":[3.983853457],"iteration":476,"passed_time":0.5667000638,"remaining_time":0.6213503844},
{"learn":[3.983263928],"iteration":477,"passed_time":0.567476393,"remaining_time":0.6197127137},
{"learn":[3.980067202],"iteration":478,"passed_time":0.5683421338,"remaining_time":0.6181758909},
{"learn":[3.978115407],"iteration":479,"passed_time":0.5691162719,"remaining_time":0.6165426279},
{"learn":[3.972661644],"iteration":480,"passed_time":0.5697841221,"remaining_time":0.6147982523},
{"learn":[3.969938254],"iteration":481,"passed_time":0.5704467067,"remaining_time":0.6130526848},
{"learn":[3.968211434],"iteration":482,"passed_time":0.5710395145,"remaining_time":0.611236913},
{"learn":[3.966113368],"iteration":483,"passed_time":0.5717259556,"remaining_time":0.6095260188},
{"learn":[3.962246044],"iteration":484,"passed_time":0.5724019058,"remaining_time":0.6078082092},
{"learn":[3.961319703],"iteration":485,"passed_time":0.5730557022,"remaining_time":0.606071257},
{"learn":[3.96078191],"iteration":486,"passed_time":0.5736955346,"remaining_time":0.6043240436},
{"learn":[3.958913633],"iteration":487,"passed_time":0.5744195913,"remaining_time":0.6026697352},
{"learn":[3.957428286],"iteration":488,"passed_time":0.5750883058,"remaining_time":0.6009613993},
{"learn":[3.952641965],"iteration":489,"passed_time":0.5757849581,"remaining_time":0.599286385},
{"learn":[3.951486786],"iteration":490,"passed_time":0.5765037422,"remaining_time":0.597638299},
{"learn":[3.94938344],"iteration":491,"passed_time":0.5772591681,"remaining_time":0.5960318239},
{"learn":[3.947297924],"iteration":492,"passed_time":0.5781262429,"remaining_time":0.594543621},
{"learn":[3.946284886],"iteration":493,"passed_time":0.5796168266,"remaining_time":0.5936965876},
{"learn":[3.943288204],"iteration":494,"passed_time":0.5805629852,"remaining_time":0.5922915303},
{"learn":[3.943076488],"iteration":495,"passed_time":0.5813183258,"remaining_time":0.5906944278},
{"learn":[3.942347078],"iteration":496,"passed_time":0.5819952527,"remaining_time":0.5890213523},
{"learn":[3.940251541],"iteration":497,"passed_time":0.5826302314,"remaining_time":0.5873099923},
{"learn":[3.939011019],"iteration":498,"passed_time":0.5833548841,"remaining_time":0.5856929798},
{"learn":[3.938760512],"iteration":499,"passed_time":0.5840239363,"remaining_time":0.5840239363},
{"learn":[3.934522727],"iteration":500,"passed_time":0.5846953986,"remaining_time":0.5823612852},
{"learn":[3.930091193],"iteration":501,"passed_time":0.5853701348,"remaining_time":0.5807058309},
{"learn":[3.927671752],"iteration":502,"passed_time":0.5860022447,"remaining_time":0.5790121583},
{"learn":[3.927280041],"iteration":503,"passed_time":0.5866144356,"remaining_time":0.5773030953},
{"learn":[3.925987561],"iteration":504,"passed_time":0.5873210971,"remaining_time":0.5756909764},
{"learn":[3.921645957],"iteration":505,"passed_time":0.5879270523,"remaining_time":0.5739841182},
{"learn":[3.920333743],"iteration":506,"passed_time":0.5885908248,"remaining_time":0.5723378237},
{"learn":[3.918659461],"iteration":507,"passed_time":0.5893032209,"remaining_time":0.5707424895},
{"learn":[3.916124385],"iteration":508,"passed_time":0.5898810758,"remaining_time":0.5690208413},
{"learn":[3.913849268],"iteration":509,"passed_time":0.5905888814,"remaining_time":0.5674285331},
{"learn":[3.912826119],"iteration":510,"passed_time":0.5911994229,"remaining_time":0.5657466101},
{"learn":[3.910034145],"iteration":511,"passed_time":0.5920229398,"remaining_time":0.5642718645},
{"learn":[3.90792379],"iteration":512,"passed_time":0.5928617862,"remaining_time":0.5628142103},
{"learn":[3.907823851],"iteration":513,"passed_time":0.5938044081,"remaining_time":0.5614570862},
{"learn":[3.904527401],"iteration":514,"passed_time":0.5947891636,"remaining_time":0.5601412512},
{"learn":[3.903378283],"iteration":515,"passed_time":0.5955804696,"remaining_time":0.5586452467},
{"learn":[3.902170135],"iteration":516,"passed_time":0.5963100605,"remaining_time":0.5570943119},
{"learn":[3.899435429],"iteration":517,"passed_time":0.5970018674,"remaining_time":0.5555113901},
{"learn":[3.897497505],"iteration":518,"passed_time":0.5977255247,"remaining_time":0.5539614208},
{"learn":[3.896426119],"iteration":519,"passed_time":0.5983747356,"remaining_time":0.5523459098},
{"learn":[3.896044669],"iteration":520,"passed_time":0.5990139679,"remaining_time":0.550724934},
{"learn":[3.892795942],"iteration":521,"passed_time":0.5996353422,"remaining_time":0.549091367},
{"learn":[3.892413888],"iteration":522,"passed_time":0.6003017202,"remaining_time":0.5475027161},
{"learn":[3.891738985],"iteration":523,"passed_time":0.6008943831,"remaining_time":0.5458506228},
{"learn":[3.88822057],"iteration":524,"passed_time":0.6015329018,"remaining_time":0.544244054},
{"learn":[3.883837053],"iteration":525,"passed_time":0.602297875,"remaining_time":0.5427551193},
{"learn":[3.881769742],"iteration":526,"passed_time":0.6030391435,"remaining_time":0.5412476563},
{"learn":[3.880356898],"iteration":527,"passed_time":0.6036706451,"remaining_time":0.5396449706},
{"learn":[3.879250273],"iteration":528,"passed_time":0.6043852671,"remaining_time":0.5381199637},
{"learn":[3.877174493],"iteration":529,"passed_time":0.6051008713,"remaining_time":0.5365988858},
{"learn":[3.875854201],"iteration":530,"passed_time":0.6057604957,"remaining_time":0.5350313983},
{"learn":[3.873189396],"iteration":531,"passed_time":0.6071372281,"remaining_time":0.534098163},
{"learn":[3.871583368],"iteration":532,"passed_time":0.6079848685,"remaining_time":0.5326996878},
{"learn":[3.869622679],"iteration":533,"passed_time":0.6087475532,"remaining_time":0.5312291382},
{"learn":[3.866860164],"iteration":534,"passed_time":0.6095962697,"remaining_time":0.5298360101},
{"learn":[3.864498444],"iteration":535,"passed_time":0.610308807,"remaining_time":0.5283270269},
{"learn":[3.861416322],"iteration":536,"passed_time":0.6110137475,"remaining_time":0.5268144602},
{"learn":[3.860265769],"iteration":537,"passed_time":0.6117049121,"remaining_time":0.5252930657},
{"learn":[3.859328725],"iteration":538,"passed_time":0.6124098878,"remaining_time":0.5237865645},
{"learn":[3.858521278],"iteration":539,"passed_time":0.6130973906,"remaining_time":0.5222681475},
{"learn":[3.85599111],"iteration":540,"passed_time":0.6138389952,"remaining_time":0.5207987039},
{"learn":[3.852379816],"iteration":541,"passed_time":0.6146206227,"remaining_time":0.5193657661},
{"learn":[3.851327537],"iteration":542,"passed_time":0.6155499627,"remaining_time":0.518059545},
{"learn":[3.847854898],"iteration":543,"passed_time":0.6166689779,"remaining_time":0.5169137021},
{"learn":[3.847083414],"iteration":544,"passed_time":0.6175289516,"remaining_time":0.5155516935},
{"learn":[3.845397429],"iteration":545,"passed_time":0.618430936,"remaining_time":0.5142264559},
{"learn":[3.841933528],"iteration":546,"passed_time":0.6191384638,"remaining_time":0.512741726},
{"learn":[3.840996474],"iteration":547,"passed_time":0.6197881883,"remaining_time":0.5112121553},
{"learn":[3.838355966],"iteration":548,"passed_time":0.6204908024,"remaining_time":0.5097292384},
{"learn":[3.83342799],"iteration":549,"passed_time":0.6211148054,"remaining_time":0.5081848408},
{"learn":[3.828161535],"iteration":550,"passed_time":0.6219366449,"remaining_time":0.5068049973},
{"learn":[3.823502399],"iteration":551,"passed_time":0.6227189064,"remaining_time":0.5053950545},
{"learn":[3.820068862],"iteration":552,"passed_time":0.6233511157,"remaining_time":0.5038660917},
{"learn":[3.817951642],"iteration":553,"passed_time":0.6239642743,"remaining_time":0.5023250295},
{"learn":[3.815785958],"iteration":554,"passed_time":0.6245778641,"remaining_time":0.5007876568},
{"learn":[3.81503012],"iteration":555,"passed_time":0.6252529906,"remaining_time":0.4993027479},
{"learn":[3.813529315],"iteration":556,"passed_time":0.6258663006,"remaining_time":0.497771582},
{"learn":[3.808881326],"iteration":557,"passed_time":0.6264997118,"remaining_time":0.4962596284},
{"learn":[3.808740434],"iteration":558,"passed_time":0.6270854966,"remaining_time":0.4947132451},
{"learn":[3.80714352],"iteration":559,"passed_time":0.6277684958,"remaining_time":0.4932466753},
{"learn":[3.80573346],"iteration":560,"passed_time":0.6284416319,"remaining_time":0.4917751807},
{"learn":[3.803370052],"iteration":561,"passed_time":0.6291035332,"remaining_time":0.4902977714},
{"learn":[3.803215211],"iteration":562,"passed_time":0.6297164347,"remaining_time":0.4887852255},
{"learn":[3.801309667],"iteration":563,"passed_time":0.6304849781,"remaining_time":0.4873961887},
{"learn":[3.800003847],"iteration":564,"passed_time":0.6317264106,"remaining_time":0.4863734312},
{"learn":[3.798026138],"iteration":565,"passed_time":0.6325932876,"remaining_time":0.4850626976},
{"learn":[3.794745847],"iteration":566,"passed_time":0.6335918921,"remaining_time":0.4838541257},
{"learn":[3.794312041],"iteration":567,"passed_time":0.6341958941,"remaining_time":0.4823461729},
{"learn":[3.792205926],"iteration":568,"passed_time":0.6347858786,"remaining_time":0.4808307798},
{"learn":[3.788991061],"iteration":569,"passed_time":0.6355074056,"remaining_time":0.4794178674},
{"learn":[3.787391572],"iteration":570,"passed_time":0.6362324624,"remaining_time":0.4780100286},
{"learn":[3.7826445],"iteration":571,"passed_time":0.6369319234,"remaining_time":0.4765854252},
{"learn":[3.781700331],"iteration":572,"passed_time":0.6376633835,"remaining_time":0.4751871985},
{"learn":[3.780045374],"iteration":573,"passed_time":0.6384746926,"remaining_time":0.4738505558},
{"learn":[3.775462644],"iteration":574,"passed_time":0.6391081469,"remaining_time":0.4723842825},
{"learn":[3.773711943],"iteration":575,"passed_time":0.6397989203,"remaining_time":0.4709630941},
{"learn":[3.772415806],"iteration":576,"passed_time":0.640489836,"remaining_time":0.4695445418},
{"learn":[3.770170875],"iteration":577,"passed_time":0.6411698477,"remaining_time":0.4681205462},
{"learn":[3.765166479],"iteration":578,"passed_time":0.6418535004,"remaining_time":0.466701768},
{"learn":[3.763976102],"iteration":579,"passed_time":0.6424707329,"remaining_time":0.4652374273},
{"learn":[3.760761708],"iteration":580,"passed_time":0.6430820277,"remaining_time":0.4637717205},
{"learn":[3.758155662],"iteration":581,"passed_time":0.6437601355,"remaining_time":0.4623569358},
{"learn":[3.756844548],"iteration":582,"passed_time":0.6444243919,"remaining_time":0.4609347708},
{"learn":[3.753098923],"iteration":583,"passed_time":0.6450807797,"remaining_time":0.4595095965},
{"learn":[3.751618946],"iteration":584,"passed_time":0.6461996488,"remaining_time":0.4584151355},
{"learn":[3.751398464],"iteration":585,"passed_time":0.6474902123,"remaining_time":0.4574418906},
{"learn":[3.749920103],"iteration":586,"passed_time":0.6483029009,"remaining_time":0.4561313426},
{"learn":[3.748237465],"iteration":587,"passed_time":0.6490763863,"remaining_time":0.4547950189},
{"learn":[3.746021536],"iteration":588,"passed_time":0.6496874728,"remaining_time":0.4533472858},
{"learn":[3.74417648],"iteration":589,"passed_time":0.6503887827,"remaining_time":0.4519650863},
{"learn":[3.738788389],"iteration":590,"passed_time":0.6510465012,"remaining_time":0.4505550237},
{"learn":[3.736021611],"iteration":591,"passed_time":0.6517529596,"remaining_time":0.4491810938},
{"learn":[3.734546151],"iteration":592,"passed_time":0.6524751062,"remaining_time":0.4478201825},
{"learn":[3.733527479],"iteration":593,"passed_time":0.6531726352,"remaining_time":0.4464445957},
{"learn":[3.733026392],"iteration":594,"passed_time":0.6538478486,"remaining_time":0.4450560986},
{"learn":[3.730314752],"iteration":595,"passed_time":0.6545226671,"remaining_time":0.4436697274},
{"learn":[3.727342596],"iteration":596,"passed_time":0.6552649555,"remaining_time":0.4423312849},
{"learn":[3.725459604],"iteration":597,"passed_time":0.6558883766,"remaining_time":0.4409149287},
{"learn":[3.723158842],"iteration":598,"passed_time":0.6565453182,"remaining_time":0.4395236604},
{"learn":[3.722362756],"iteration":599,"passed_time":0.6571809699,"remaining_time":0.4381206466},
{"learn":[3.721443615],"iteration":600,"passed_time":0.6578385956,"remaining_time":0.4367347748},
{"learn":[3.720743486],"iteration":601,"passed_time":0.6584734501,"remaining_time":0.4353362677},
{"learn":[3.720215334],"iteration":602,"passed_time":0.6591073407,"remaining_time":0.4339396588},
{"learn":[3.719436563],"iteration":603,"passed_time":0.6597179641,"remaining_time":0.4325303208},
{"learn":[3.715046574],"iteration":604,"passed_time":0.660416349,"remaining_time":0.4311809221},
{"learn":[3.71443396],"iteration":605,"passed_time":0.6614151306,"remaining_time":0.4300289793},
{"learn":[3.712938941],"iteration":606,"passed_time":0.6622655292,"remaining_time":0.4287814712},
{"learn":[3.712814764],"iteration":607,"passed_time":0.6630720086,"remaining_time":0.4275069529},
{"learn":[3.71235348],"iteration":608,"passed_time":0.6637840707,"remaining_time":0.4261733524},
{"learn":[3.711223749],"iteration":609,"passed_time":0.6645323221,"remaining_time":0.4248649272},
{"learn":[3.710755648],"iteration":610,"passed_time":0.6653572007,"remaining_time":0.4236071213},
{"learn":[3.708668039],"iteration":611,"passed_time":0.6662501395,"remaining_time":0.4223938793},
{"learn":[3.705623591],"iteration":612,"passed_time":0.6673146273,"remaining_time":0.421289985},
{"learn":[3.704045802],"iteration":613,"passed_time":0.6680073622,"remaining_time":0.4199525111},
{"learn":[3.699915209],"iteration":614,"passed_time":0.6687772069,"remaining_time":0.4186654059},
{"learn":[3.696182221],"iteration":615,"passed_time":0.6696500974,"remaining_time":0.4174442165},
{"learn":[3.694263278],"iteration":616,"passed_time":0.670440405,"remaining_time":0.4161728932},
{"learn":[3.693810229],"iteration":617,"passed_time":0.6712041059,"remaining_time":0.4148866803},
{"learn":[3.690900932],"iteration":618,"passed_time":0.6719598496,"remaining_time":0.413597258},
{"learn":[3.688020895],"iteration":619,"passed_time":0.6726819341,"remaining_time":0.4122889274},
{"learn":[3.685491894],"iteration":620,"passed_time":0.6734503294,"remaining_time":0.4110107485},
{"learn":[3.684328128],"iteration":621,"passed_time":0.6741744242,"remaining_time":0.4097072867},
{"learn":[3.680640153],"iteration":622,"passed_time":0.6749391142,"remaining_time":0.4084302505},
{"learn":[3.678932783],"iteration":623,"passed_time":0.6761767621,"remaining_time":0.4074398438},
{"learn":[3.674167041],"iteration":624,"passed_time":0.6777506893,"remaining_time":0.4066504136},
{"learn":[3.672200976],"iteration":625,"passed_time":0.67886311,"remaining_time":0.4055827526},
{"learn":[3.670606604],"iteration":626,"passed_time":0.6796466211,"remaining_time":0.4043192818},
{"learn":[3.665506042],"iteration":627,"passed_time":0.6804198407,"remaining_time":0.4030512432},
{"learn":[3.664214007],"iteration":628,"passed_time":0.6811549778,"remaining_time":0.401762316},
{"learn":[3.66261643],"iteration":629,"passed_time":0.6819918681,"remaining_time":0.4005349067},
{"learn":[3.662118449],"iteration":630,"passed_time":0.6827345588,"remaining_time":0.3992536485},
{"learn":[3.660871366],"iteration":631,"passed_time":0.6835221588,"remaining_time":0.3980002444},
{"learn":[3.656695243],"iteration":632,"passed_time":0.6842940519,"remaining_time":0.3967392054},
{"learn":[3.654497801],"iteration":633,"passed_time":0.685036017,"remaining_time":0.3954624325},
{"learn":[3.654189134],"iteration":634,"passed_time":0.6858260846,"remaining_time":0.3942149935},
{"learn":[3.653957699],"iteration":635,"passed_time":0.6866378155,"remaining_time":0.3929813913},
{"learn":[3.651920725],"iteration":636,"passed_time":0.6874632513,"remaining_time":0.3917569234},
{"learn":[3.65106705],"iteration":637,"passed_time":0.6882652424,"remaining_time":0.390520404},
{"learn":[3.650612844],"iteration":638,"passed_time":0.6890274271,"remaining_time":0.3892627562},
{"learn":[3.649884732],"iteration":639,"passed_time":0.6898042174,"remaining_time":0.3880148723},
{"learn":[3.646276182],"iteration":640,"passed_time":0.6906378011,"remaining_time":0.3868002662},
{"learn":[3.645808194],"iteration":641,"passed_time":0.6922894421,"remaining_time":0.3860430222},
{"learn":[3.645042989],"iteration":642,"passed_time":0.6931189431,"remaining_time":0.3848265361},
{"learn":[3.639864499],"iteration":643,"passed_time":0.6938864655,"remaining_time":0.3835769902},
{"learn":[3.637318478],"iteration":644,"passed_time":0.69460065,"remaining_time":0.3822995826},
{"learn":[3.636344905],"iteration":645,"passed_time":0.6953426495,"remaining_time":0.3810391609},
{"learn":[3.634754643],"iteration":646,"passed_time":0.6960612118,"remaining_time":0.3797675545},
{"learn":[3.630724975],"iteration":647,"passed_time":0.6968598594,"remaining_time":0.3785411582},
{"learn":[3.629408252],"iteration":648,"passed_time":0.6975982394,"remaining_time":0.3772834854},
{"learn":[3.62790646],"iteration":649,"passed_time":0.6984065967,"remaining_time":0.3760650905},
{"learn":[3.627388973],"iteration":650,"passed_time":0.6991815261,"remaining_time":0.3748300347},
{"learn":[3.625163557],"iteration":651,"passed_time":0.6999326987,"remaining_time":0.3735837104},
{"learn":[3.623701985],"iteration":652,"passed_time":0.7007448567,"remaining_time":0.3723713098},
{"learn":[3.622342639],"iteration":653,"passed_time":0.7014000732,"remaining_time":0.371077103},
{"learn":[3.621130639],"iteration":654,"passed_time":0.7021629244,"remaining_time":0.3698415403},
{"learn":[3.619125665],"iteration":655,"passed_time":0.7028818786,"remaining_time":0.3685843998},
{"learn":[3.618878783],"iteration":656,"passed_time":0.7036272948,"remaining_time":0.3673427125},
{"learn":[3.616207429],"iteration":657,"passed_time":0.7043379658,"remaining_time":0.3660844746},
{"learn":[3.61206486],"iteration":658,"passed_time":0.7050517298,"remaining_time":0.364829499},
{"learn":[3.611955873],"iteration":659,"passed_time":0.7058770571,"remaining_time":0.3636336355},
{"learn":[3.610713743],"iteration":660,"passed_time":0.7075226999,"remaining_time":0.3628595995},
{"learn":[3.610044025],"iteration":661,"passed_time":0.7084097365,"remaining_time":0.3616956056},
{"learn":[3.607342669],"iteration":662,"passed_time":0.709198336,"remaining_time":0.3604824121},
{"learn":[3.602510618],"iteration":663,"passed_time":0.7099622538,"remaining_time":0.3592580079},
{"learn":[3.600492392],"iteration":664,"passed_time":0.7107327698,"remaining_time":0.3580383126},
{"learn":[3.597171065],"iteration":665,"passed_time":0.7114845828,"remaining_time":0.3568105865},
{"learn":[3.594358798],"iteration":666,"passed_time":0.7122670624,"remaining_time":0.3555995979},
{"learn":[3.593945251],"iteration":667,"passed_time":0.7129899185,"remaining_time":0.3543602589},
{"learn":[3.593607748],"iteration":668,"passed_time":0.7137367564,"remaining_time":0.3531343294},
{"learn":[3.592238714],"iteration":669,"passed_time":0.714441978,"remaining_time":0.3518893325},
{"learn":[3.590144654],"iteration":670,"passed_time":0.7151608275,"remaining_time":0.3506526263},
{"learn":[3.587151536],"iteration":671,"passed_time":0.7158585664,"remaining_time":0.3494071574},
{"learn":[3.586070865],"iteration":672,"passed_time":0.7165310597,"remaining_time":0.3481510498},
{"learn":[3.585102746],"iteration":673,"passed_time":0.7172420895,"remaining_time":0.3469153133},
{"learn":[3.584362847],"iteration":674,"passed_time":0.7179416734,"remaining_time":0.3456756205},
{"learn":[3.581407561],"iteration":675,"passed_time":0.7186659802,"remaining_time":0.3444493751},
{"learn":[3.57919422],"iteration":676,"passed_time":0.719383208,"remaining_time":0.3432212352},
{"learn":[3.577632204],"iteration":677,"passed_time":0.7201167355,"remaining_time":0.3420023434},
{"learn":[3.573911195],"iteration":678,"passed_time":0.7210904078,"remaining_time":0.3408984108},
{"learn":[3.573408216],"iteration":679,"passed_time":0.7222087836,"remaining_time":0.339862957},
{"learn":[3.571076482],"iteration":680,"passed_time":0.7231796111,"remaining_time":0.3387581438},
{"learn":[3.568177107],"iteration":681,"passed_time":0.723962544,"remaining_time":0.3375661129},
{"learn":[3.564824621],"iteration":682,"passed_time":0.7246880672,"remaining_time":0.3363486344},
{"learn":[3.562475026],"iteration":683,"passed_time":0.7254668711,"remaining_time":0.3351572094},
{"learn":[3.561226889],"iteration":684,"passed_time":0.7262654248,"remaining_time":0.3339760712},
{"learn":[3.559383467],"iteration":685,"passed_time":0.7270283297,"remaining_time":0.3327797311},
{"learn":[3.555209766],"iteration":686,"passed_time":0.7278201353,"remaining_time":0.33159782},
{"learn":[3.55345383],"iteration":687,"passed_time":0.7286265492,"remaining_time":0.3304236677},
{"learn":[3.552300968],"iteration":688,"passed_time":0.7294762355,"remaining_time":0.329270115},
{"learn":[3.551253986],"iteration":689,"passed_time":0.7303073106,"remaining_time":0.3281090816},
{"learn":[3.549807725],"iteration":690,"passed_time":0.731102518,"remaining_time":0.3269329639},
{"learn":[3.547992926],"iteration":691,"passed_time":0.7319497888,"remaining_time":0.3257811199},
{"learn":[3.545438607],"iteration":692,"passed_time":0.7327706258,"remaining_time":0.3246184446},
{"learn":[3.543313763],"iteration":693,"passed_time":0.7335922827,"remaining_time":0.323457116},
{"learn":[3.542962896],"iteration":694,"passed_time":0.7344496326,"remaining_time":0.3223124287},
{"learn":[3.539800465],"iteration":695,"passed_time":0.7353363729,"remaining_time":0.3211814043},
{"learn":[3.53953187],"iteration":696,"passed_time":0.7360816831,"remaining_time":0.3199895983},
{"learn":[3.536332425],"iteration":697,"passed_time":0.7381015934,"remaining_time":0.3193505461},
{"learn":[3.534993327],"iteration":698,"passed_time":0.7389100462,"remaining_time":0.3181858711},
{"learn":[3.531637011],"iteration":699,"passed_time":0.7397438741,"remaining_time":0.3170330889},
{"learn":[3.531040284],"iteration":700,"passed_time":0.7404690836,"remaining_time":0.3158348873},
{"learn":[3.529973872],"iteration":701,"passed_time":0.7411809014,"remaining_time":0.3146323485},
{"learn":[3.527325183],"iteration":702,"passed_time":0.7419745902,"remaining_time":0.3134657942},
{"learn":[3.527200815],"iteration":703,"passed_time":0.7426368073,"remaining_time":0.3122450213},
{"learn":[3.523459911],"iteration":704,"passed_time":0.743313779,"remaining_time":0.3110320068},
{"learn":[3.522729934],"iteration":705,"passed_time":0.7440541345,"remaining_time":0.3098469059},
{"learn":[3.522260582],"iteration":706,"passed_time":0.74469823,"remaining_time":0.3086231703},
{"learn":[3.518641591],"iteration":707,"passed_time":0.7454252076,"remaining_time":0.3074352551},
{"learn":[3.516856405],"iteration":708,"passed_time":0.7462287603,"remaining_time":0.3062800695},
{"learn":[3.515083413],"iteration":709,"passed_time":0.7469534048,"remaining_time":0.3050936442},
{"learn":[3.514671214],"iteration":710,"passed_time":0.7476614322,"remaining_time":0.3039017636},
{"learn":[3.512617621],"iteration":711,"passed_time":0.7485066211,"remaining_time":0.3027667232},
{"learn":[3.510747971],"iteration":712,"passed_time":0.7493268365,"remaining_time":0.3016224433},
{"learn":[3.508149266],"iteration":713,"passed_time":0.7500562879,"remaining_time":0.3004427148},
{"learn":[3.504557165],"iteration":714,"passed_time":0.7508091054,"remaining_time":0.2992735595},
{"learn":[3.501367208],"iteration":715,"passed_time":0.7515417277,"remaining_time":0.2980975568},
{"learn":[3.497593362],"iteration":716,"passed_time":0.7526558449,"remaining_time":0.2970733669},
{"learn":[3.496291169],"iteration":717,"passed_time":0.7538612445,"remaining_time":0.2960847785},
{"learn":[3.49330374],"iteration":718,"passed_time":0.7546093626,"remaining_time":0.2949168719},
{"learn":[3.490044385],"iteration":719,"passed_time":0.7554043461,"remaining_time":0.2937683568},
{"learn":[3.488891789],"iteration":720,"passed_time":0.7561692315,"remaining_time":0.2926091756},
{"learn":[3.486869081],"iteration":721,"passed_time":0.7569376429,"remaining_time":0.2914524442},
{"learn":[3.486303638],"iteration":722,"passed_time":0.757656927,"remaining_time":0.2902779651},
{"learn":[3.486035862],"iteration":723,"passed_time":0.7583276306,"remaining_time":0.2890862238},
{"learn":[3.482668951],"iteration":724,"passed_time":0.7591019259,"remaining_time":0.2879352133},
{"learn":[3.47820549],"iteration":725,"passed_time":0.759852503,"remaining_time":0.286776289},
{"learn":[3.474392283],"iteration":726,"passed_time":0.7606058101,"remaining_time":0.2856195133},
{"learn":[3.472268163],"iteration":727,"passed_time":0.7612997183,"remaining_time":0.284441653},
{"learn":[3.471209164],"iteration":728,"passed_time":0.7619147986,"remaining_time":0.2832358168},
{"learn":[3.470049971],"iteration":729,"passed_time":0.7625638124,"remaining_time":0.2820441498},
{"learn":[3.469078654],"iteration":730,"passed_time":0.7632979074,"remaining_time":0.2808852765},
{"learn":[3.468643292],"iteration":731,"passed_time":0.7639334299,"remaining_time":0.2796914743},
{"learn":[3.468134848],"iteration":732,"passed_time":0.7645878616,"remaining_time":0.2785060833},
{"learn":[3.467820182],"iteration":733,"passed_time":0.7652763507,"remaining_time":0.2773344813},
{"learn":[3.465776156],"iteration":734,"passed_time":0.7659444278,"remaining_time":0.2761568345},
{"learn":[3.463037608],"iteration":735,"passed_time":0.7666079751,"remaining_time":0.2749789476},
{"learn":[3.45965637],"iteration":736,"passed_time":0.7674375374,"remaining_time":0.2738616992},
{"learn":[3.457275091],"iteration":737,"passed_time":0.7683254271,"remaining_time":0.2727659375},
{"learn":[3.455522955],"iteration":738,"passed_time":0.7690322318,"remaining_time":0.2716067828},
{"learn":[3.451270508],"iteration":739,"passed_time":0.769809604,"remaining_time":0.2704736447},
{"learn":[3.450978947],"iteration":740,"passed_time":0.7704597677,"remaining_time":0.2692970038},
{"learn":[3.450608492],"iteration":741,"passed_time":0.7710913202,"remaining_time":0.2681153108},
{"learn":[3.448122004],"iteration":742,"passed_time":0.7717687897,"remaining_time":0.2669509811},
{"learn":[3.445646714],"iteration":743,"passed_time":0.7724188371,"remaining_time":0.2657785246},
{"learn":[3.44411263],"iteration":744,"passed_time":0.7730746963,"remaining_time":0.2646094598},
{"learn":[3.443264164],"iteration":745,"passed_time":0.7737582692,"remaining_time":0.2634512069},
{"learn":[3.439521363],"iteration":746,"passed_time":0.7744190674,"remaining_time":0.2622865115},
{"learn":[3.436809225],"iteration":747,"passed_time":0.7751247009,"remaining_time":0.2611382682},
{"learn":[3.435509465],"iteration":748,"passed_time":0.7758911686,"remaining_time":0.2600115932},
{"learn":[3.434450277],"iteration":749,"passed_time":0.7766732133,"remaining_time":0.2588910711},
{"learn":[3.431786753],"iteration":750,"passed_time":0.7774575,"remaining_time":0.2577721938},
{"learn":[3.430150302],"iteration":751,"passed_time":0.7781540795,"remaining_time":0.2566252815},
{"learn":[3.42696281],"iteration":752,"passed_time":0.7788558985,"remaining_time":0.2554812841},
{"learn":[3.426870334],"iteration":753,"passed_time":0.7794903656,"remaining_time":0.2543164853},
{"learn":[3.425200309],"iteration":754,"passed_time":0.7801644963,"remaining_time":0.2531659624},
{"learn":[3.423383783],"iteration":755,"passed_time":0.7808301466,"remaining_time":0.2520139627},
{"learn":[3.422752979],"iteration":756,"passed_time":0.7815258379,"remaining_time":0.2508728912},
{"learn":[3.420845924],"iteration":757,"passed_time":0.7822328298,"remaining_time":0.2497366026},
{"learn":[3.418917862],"iteration":758,"passed_time":0.7837065004,"remaining_time":0.2488448835},
{"learn":[3.417095735],"iteration":759,"passed_time":0.7844855278,"remaining_time":0.2477322719},
{"learn":[3.414391848],"iteration":760,"passed_time":0.7851763198,"remaining_time":0.2465928258},
{"learn":[3.41426711],"iteration":761,"passed_time":0.7857745169,"remaining_time":0.2454256365},
{"learn":[3.411976013],"iteration":762,"passed_time":0.7864431833,"remaining_time":0.2442818276},
{"learn":[3.408614844],"iteration":763,"passed_time":0.7870197899,"remaining_time":0.2431108252},
{"learn":[3.407906721],"iteration":764,"passed_time":0.7876765114,"remaining_time":0.2419659871},
{"learn":[3.407494015],"iteration":765,"passed_time":0.7882981456,"remaining_time":0.2408117051},
{"learn":[3.406287128],"iteration":766,"passed_time":0.788904854,"remaining_time":0.2396542777},
{"learn":[3.404600442],"iteration":767,"passed_time":0.7895388472,"remaining_time":0.2385065268},
{"learn":[3.404012662],"iteration":768,"passed_time":0.7902141223,"remaining_time":0.2373725127},
{"learn":[3.400398762],"iteration":769,"passed_time":0.7909221882,"remaining_time":0.2362494848},
{"learn":[3.399737714],"iteration":770,"passed_time":0.7915791973,"remaining_time":0.2351123686},
{"learn":[3.399185251],"iteration":771,"passed_time":0.7922608977,"remaining_time":0.2339837884},
{"learn":[3.397245411],"iteration":772,"passed_time":0.7929622419,"remaining_time":0.2328621331},
{"learn":[3.396229831],"iteration":773,"passed_time":0.7937529825,"remaining_time":0.2317676667},
{"learn":[3.394002836],"iteration":774,"passed_time":0.7944875514,"remaining_time":0.2306576762},
{"learn":[3.389617243],"iteration":775,"passed_time":0.7953356053,"remaining_time":0.2295814118},
{"learn":[3.385426488],"iteration":776,"passed_time":0.7960698447,"remaining_time":0.22847307},
{"learn":[3.385072258],"iteration":777,"passed_time":0.7967196627,"remaining_time":0.2273416004},
{"learn":[3.383842366],"iteration":778,"passed_time":0.797412941,"remaining_time":0.226223697},
{"learn":[3.380110746],"iteration":779,"passed_time":0.7983712292,"remaining_time":0.2251816287},
{"learn":[3.378595218],"iteration":780,"passed_time":0.7993708928,"remaining_time":0.2241513771},
{"learn":[3.377371219],"iteration":781,"passed_time":0.8000983456,"remaining_time":0.2230453188},
{"learn":[3.375814782],"iteration":782,"passed_time":0.8007024862,"remaining_time":0.221906053},
{"learn":[3.374195887],"iteration":783,"passed_time":0.8013526146,"remaining_time":0.2207808224},
{"learn":[3.373704309],"iteration":784,"passed_time":0.8020125619,"remaining_time":0.2196594915},
{"learn":[3.372971757],"iteration":785,"passed_time":0.8026796618,"remaining_time":0.218541282},
{"learn":[3.371565136],"iteration":786,"passed_time":0.8033649369,"remaining_time":0.217429138},
{"learn":[3.3700309],"iteration":787,"passed_time":0.8039863295,"remaining_time":0.2163008907},
{"learn":[3.368186663],"iteration":788,"passed_time":0.8047412012,"remaining_time":0.2152096241},
{"learn":[3.366710398],"iteration":789,"passed_time":0.8053811383,"remaining_time":0.214088657},
{"learn":[3.364598042],"iteration":790,"passed_time":0.8060855015,"remaining_time":0.212985929},
{"learn":[3.36348442],"iteration":791,"passed_time":0.8068394551,"remaining_time":0.2118972306},
{"learn":[3.362001759],"iteration":792,"passed_time":0.8075078562,"remaining_time":0.2107870444},
{"learn":[3.361580401],"iteration":793,"passed_time":0.8081895016,"remaining_time":0.2096814072},
{"learn":[3.359543675],"iteration":794,"passed_time":0.8089156137,"remaining_time":0.2085883029},
{"learn":[3.35766119],"iteration":795,"passed_time":0.809602888,"remaining_time":0.2074861673},
{"learn":[3.354592969],"iteration":796,"passed_time":0.810363389,"remaining_time":0.2064037239},
{"learn":[3.350985986],"iteration":797,"passed_time":0.8110479987,"remaining_time":0.2053028769},
{"learn":[3.349589624],"iteration":798,"passed_time":0.8117883091,"remaining_time":0.204217084},
{"learn":[3.349110856],"iteration":799,"passed_time":0.812499766,"remaining_time":0.2031249415},
{"learn":[3.345315441],"iteration":800,"passed_time":0.8134689045,"remaining_time":0.2020977678},
{"learn":[3.34397474],"iteration":801,"passed_time":0.8143309828,"remaining_time":0.2010443075},
{"learn":[3.343800902],"iteration":802,"passed_time":0.8150389374,"remaining_time":0.1999535127},
{"learn":[3.342329465],"iteration":803,"passed_time":0.8156911093,"remaining_time":0.1988500714},
{"learn":[3.34220347],"iteration":804,"passed_time":0.8163053162,"remaining_time":0.1977385549},
{"learn":[3.341279219],"iteration":805,"passed_time":0.8169935867,"remaining_time":0.196646099},
{"learn":[3.337329521],"iteration":806,"passed_time":0.8176779183,"remaining_time":0.1955537029},
{"learn":[3.336708453],"iteration":807,"passed_time":0.818366904,"remaining_time":0.1944634227},
{"learn":[3.333252703],"iteration":808,"passed_time":0.8191735825,"remaining_time":0.1934019212},
{"learn":[3.332186769],"iteration":809,"passed_time":0.8199208393,"remaining_time":0.1923271104},
{"learn":[3.330594851],"iteration":810,"passed_time":0.8206099393,"remaining_time":0.1912395543},
{"learn":[3.327867442],"iteration":811,"passed_time":0.8213444436,"remaining_time":0.1901634919},
{"learn":[3.327563111],"iteration":812,"passed_time":0.8220203006,"remaining_time":0.1890747801},
{"learn":[3.326308994],"iteration":813,"passed_time":0.8227758253,"remaining_time":0.1880052869},
{"learn":[3.326249879],"iteration":814,"passed_time":0.823445743,"remaining_time":0.1869171318},
{"learn":[3.322336238],"iteration":815,"passed_time":0.824187538,"remaining_time":0.1858462095},
{"learn":[3.320491154],"iteration":816,"passed_time":0.8248628648,"remaining_time":0.1847612047},
{"learn":[3.320434271],"iteration":817,"passed_time":0.8255036434,"remaining_time":0.1836695148},
{"learn":[3.319609638],"iteration":818,"passed_time":0.8262035291,"remaining_time":0.1825919887},
{"learn":[3.316182682],"iteration":819,"passed_time":0.8269738667,"remaining_time":0.1815308488},
{"learn":[3.313126612],"iteration":820,"passed_time":0.8276672986,"remaining_time":0.1804536497},
{"learn":[3.311222803],"iteration":821,"passed_time":0.8289364078,"remaining_time":0.1795020445},
{"learn":[3.309627335],"iteration":822,"passed_time":0.8298722236,"remaining_time":0.1784779873},
{"learn":[3.307974895],"iteration":823,"passed_time":0.8305719404,"remaining_time":0.1774037154},
{"learn":[3.307321505],"iteration":824,"passed_time":0.8311946922,"remaining_time":0.1763140256},
{"learn":[3.306759087],"iteration":825,"passed_time":0.831983764,"remaining_time":0.1752605023},
{"learn":[3.30484037],"iteration":826,"passed_time":0.832704402,"remaining_time":0.174193303},
{"learn":[3.30201994],"iteration":827,"passed_time":0.8335072018,"remaining_time":0.1731440081},
{"learn":[3.299302297],"iteration":828,"passed_time":0.8342797013,"remaining_time":0.1720890578},
{"learn":[3.298132671],"iteration":829,"passed_time":0.8350363332,"remaining_time":0.1710315381},
{"learn":[3.296976183],"iteration":830,"passed_time":0.8357150333,"remaining_time":0.1699588936},
{"learn":[3.293144745],"iteration":831,"passed_time":0.8363844298,"remaining_time":0.1688853176},
{"learn":[3.290284404],"iteration":832,"passed_time":0.8370705949,"remaining_time":0.1678160736},
{"learn":[3.288285745],"iteration":833,"passed_time":0.8377701316,"remaining_time":0.1667504099},
{"learn":[3.286662667],"iteration":834,"passed_time":0.8384715173,"remaining_time":0.1656859884},
{"learn":[3.285692682],"iteration":835,"passed_time":0.8391606897,"remaining_time":0.1646200396},
{"learn":[3.284565611],"iteration":836,"passed_time":0.8398287274,"remaining_time":0.1635508752},
{"learn":[3.283897383],"iteration":837,"passed_time":0.8405462852,"remaining_time":0.1624922413},
{"learn":[3.280712855],"iteration":838,"passed_time":0.8412294123,"remaining_time":0.1614278133},
{"learn":[3.280468341],"iteration":839,"passed_time":0.8418237146,"remaining_time":0.1603473742},
{"learn":[3.277814895],"iteration":840,"passed_time":0.8425510295,"remaining_time":0.1592932386},
{"learn":[3.276316385],"iteration":841,"passed_time":0.8435243011,"remaining_time":0.1582860328},
{"learn":[3.27557063],"iteration":842,"passed_time":0.8445998805,"remaining_time":0.1572979611},
{"learn":[3.27499628],"iteration":843,"passed_time":0.8453823246,"remaining_time":0.1562555008},
{"learn":[3.273569958],"iteration":844,"passed_time":0.846071908,"remaining_time":0.1551966222},
{"learn":[3.269665595],"iteration":845,"passed_time":0.8468097044,"remaining_time":0.154147393},
{"learn":[3.267984685],"iteration":846,"passed_time":0.8474630907,"remaining_time":0.1530836516},
{"learn":[3.267702508],"iteration":847,"passed_time":0.8481330108,"remaining_time":0.1520238416},
{"learn":[3.266671924],"iteration":848,"passed_time":0.8488477855,"remaining_time":0.1509729277},
{"learn":[3.265359825],"iteration":849,"passed_time":0.8495910358,"remaining_time":0.1499278299},
{"learn":[3.2618983],"iteration":850,"passed_time":0.8502820381,"remaining_time":0.1488742934},
{"learn":[3.260456253],"iteration":851,"passed_time":0.8509911081,"remaining_time":0.1478247465},
{"learn":[3.258389147],"iteration":852,"passed_time":0.8516960388,"remaining_time":0.1467752845},
{"learn":[3.258108469],"iteration":853,"passed_time":0.8523769589,"remaining_time":0.1457225246},
{"learn":[3.256424936],"iteration":854,"passed_time":0.8530416085,"remaining_time":0.1446678751},
{"learn":[3.254817983],"iteration":855,"passed_time":0.8537298012,"remaining_time":0.1436180974},
{"learn":[3.253898449],"iteration":856,"passed_time":0.8543555708,"remaining_time":0.1425587475},
{"learn":[3.253023652],"iteration":857,"passed_time":0.8549787253,"remaining_time":0.1414999755},
{"learn":[3.252845542],"iteration":858,"passed_time":0.855610882,"remaining_time":0.1404436954},
{"learn":[3.252316026],"iteration":859,"passed_time":0.8563254188,"remaining_time":0.1394018124},
{"learn":[3.24975301],"iteration":860,"passed_time":0.8569354375,"remaining_time":0.1383438163},
{"learn":[3.249151075],"iteration":861,"passed_time":0.8575465717,"remaining_time":0.1372870382},
{"learn":[3.246257135],"iteration":862,"passed_time":0.8583665726,"remaining_time":0.1362644501},
{"learn":[3.243826471],"iteration":863,"passed_time":0.8593932098,"remaining_time":0.1352748571},
{"learn":[3.243190653],"iteration":864,"passed_time":0.8601734975,"remaining_time":0.1342467308},
{"learn":[3.24008797],"iteration":865,"passed_time":0.8609279515,"remaining_time":0.1332151796},
{"learn":[3.240036811],"iteration":866,"passed_time":0.8616068341,"remaining_time":0.1321726747},
{"learn":[3.238676314],"iteration":867,"passed_time":0.8622653729,"remaining_time":0.1311279138},
{"learn":[3.237848782],"iteration":868,"passed_time":0.8628680177,"remaining_time":0.130075616},
{"learn":[3.236405498],"iteration":869,"passed_time":0.8635163233,"remaining_time":0.1290311748},
{"learn":[3.233378068],"iteration":870,"passed_time":0.8642083367,"remaining_time":0.1279941165},
{"learn":[3.233169169],"iteration":871,"passed_time":0.864902103,"remaining_time":0.1269581069},
{"learn":[3.232434885],"iteration":872,"passed_time":0.8656343677,"remaining_time":0.1259284819},
{"learn":[3.229978115],"iteration":873,"passed_time":0.8663840913,"remaining_time":0.1249020544},
{"learn":[3.229648848],"iteration":874,"passed_time":0.8671313796,"remaining_time":0.1238759114},
{"learn":[3.227208761],"iteration":875,"passed_time":0.8678101707,"remaining_time":0.1228407091},
{"learn":[3.226258869],"iteration":876,"passed_time":0.8684605301,"remaining_time":0.121802332},
{"learn":[3.225331995],"iteration":877,"passed_time":0.8691471451,"remaining_time":0.1207698766},
{"learn":[3.221968268],"iteration":878,"passed_time":0.8698878056,"remaining_time":0.1197456479},
{"learn":[3.221166317],"iteration":879,"passed_time":0.8706352648,"remaining_time":0.1187229907},
{"learn":[3.220047503],"iteration":880,"passed_time":0.8713425923,"remaining_time":0.1176955374},
{"learn":[3.21982781],"iteration":881,"passed_time":0.8721025988,"remaining_time":0.1166758579},
{"learn":[3.216693405],"iteration":882,"passed_time":0.87281696,"remaining_time":0.1156507184},
{"learn":[3.214798761],"iteration":883,"passed_time":0.8740208183,"remaining_time":0.1146905146},
{"learn":[3.214395085],"iteration":884,"passed_time":0.8749961996,"remaining_time":0.1137000711},
{"learn":[3.213470696],"iteration":885,"passed_time":0.8756594597,"remaining_time":0.1126695016},
{"learn":[3.211595017],"iteration":886,"passed_time":0.8763104515,"remaining_time":0.1116381973},
{"learn":[3.210965255],"iteration":887,"passed_time":0.8769697068,"remaining_time":0.1106087919},
{"learn":[3.209413583],"iteration":888,"passed_time":0.8776706699,"remaining_time":0.1095854267},
{"learn":[3.208331683],"iteration":889,"passed_time":0.8783950755,"remaining_time":0.1085656835},
{"learn":[3.207110711],"iteration":890,"passed_time":0.8790385593,"remaining_time":0.1075367037},
{"learn":[3.204519413],"iteration":891,"passed_time":0.8797370134,"remaining_time":0.1065152438},
{"learn":[3.201421296],"iteration":892,"passed_time":0.8804306393,"remaining_time":0.1054939288},
{"learn":[3.200691259],"iteration":893,"passed_time":0.8810780721,"remaining_time":0.1044678698},
{"learn":[3.200485067],"iteration":894,"passed_time":0.8816959362,"remaining_time":0.103439188},
{"learn":[3.197467568],"iteration":895,"passed_time":0.8823815458,"remaining_time":0.1024192866},
{"learn":[3.195838544],"iteration":896,"passed_time":0.8829868933,"remaining_time":0.1013909142},
{"learn":[3.195671746],"iteration":897,"passed_time":0.8835642454,"remaining_time":0.100360304},
{"learn":[3.194213094],"iteration":898,"passed_time":0.8842074324,"remaining_time":0.09933809864},
{"learn":[3.192884691],"iteration":899,"passed_time":0.8848080342,"remaining_time":0.0983120038},
{"learn":[3.188364239],"iteration":900,"passed_time":0.8854351373,"remaining_time":0.09728976536},
{"learn":[3.185219478],"iteration":901,"passed_time":0.8861183972,"remaining_time":0.09627450436},
{"learn":[3.184120387],"iteration":902,"passed_time":0.8867646256,"remaining_time":0.09525600076},
{"learn":[3.183725321],"iteration":903,"passed_time":0.887410868,"remaining_time":0.09423832227},
{"learn":[3.181264554],"iteration":904,"passed_time":0.8880883098,"remaining_time":0.0932247397},
{"learn":[3.180741589],"iteration":905,"passed_time":0.889297478,"remaining_time":0.09226706725},
{"learn":[3.179782639],"iteration":906,"passed_time":0.8907166457,"remaining_time":0.09133037272},
{"learn":[3.176377564],"iteration":907,"passed_time":0.8913982778,"remaining_time":0.09031788718},
{"learn":[3.174078182],"iteration":908,"passed_time":0.8920887424,"remaining_time":0.08930701382},
{"learn":[3.171242379],"iteration":909,"passed_time":0.8928857391,"remaining_time":0.08830738079},
{"learn":[3.170421012],"iteration":910,"passed_time":0.8936103339,"remaining_time":0.08730111934},
{"learn":[3.170087224],"iteration":911,"passed_time":0.8943312363,"remaining_time":0.08629511929},
{"learn":[3.167303059],"iteration":912,"passed_time":0.8951247922,"remaining_time":0.08529666695},
{"learn":[3.16705966],"iteration":913,"passed_time":0.8958860395,"remaining_time":0.08429562297},
{"learn":[3.165667683],"iteration":914,"passed_time":0.8965517685,"remaining_time":0.08328622986},
{"learn":[3.164689733],"iteration":915,"passed_time":0.8972158597,"remaining_time":0.08227743692},
{"learn":[3.163311455],"iteration":916,"passed_time":0.8979152289,"remaining_time":0.08127258887},
{"learn":[3.159425016],"iteration":917,"passed_time":0.8985859677,"remaining_time":0.08026584896},
{"learn":[3.159327058],"iteration":918,"passed_time":0.8992100663,"remaining_time":0.07925572946},
{"learn":[3.15819426],"iteration":919,"passed_time":0.8999231441,"remaining_time":0.07825418644},
{"learn":[3.157086603],"iteration":920,"passed_time":0.9006110508,"remaining_time":0.07725111076},
{"learn":[3.153354154],"iteration":921,"passed_time":0.9012904301,"remaining_time":0.07624799734},
{"learn":[3.153261317],"iteration":922,"passed_time":0.9019231381,"remaining_time":0.07524169191},
{"learn":[3.153168454],"iteration":923,"passed_time":0.9026705472,"remaining_time":0.07424562942},
{"learn":[3.152080399],"iteration":924,"passed_time":0.9034392856,"remaining_time":0.07325183397},
{"learn":[3.151635144],"iteration":925,"passed_time":0.9047759251,"remaining_time":0.07230390762},
{"learn":[3.147762655],"iteration":926,"passed_time":0.9055628981,"remaining_time":0.07131185713},
{"learn":[3.147172317],"iteration":927,"passed_time":0.9062556043,"remaining_time":0.07031293482},
{"learn":[3.146254125],"iteration":928,"passed_time":0.9068524297,"remaining_time":0.06930734393},
{"learn":[3.144869828],"iteration":929,"passed_time":0.907526067,"remaining_time":0.06830841365},
{"learn":[3.143466218],"iteration":930,"passed_time":0.9080944438,"remaining_time":0.0673023809},
{"learn":[3.141919643],"iteration":931,"passed_time":0.9087734075,"remaining_time":0.06630535591},
{"learn":[3.141054135],"iteration":932,"passed_time":0.9094104879,"remaining_time":0.06530600503},
{"learn":[3.139390417],"iteration":933,"passed_time":0.9100393948,"remaining_time":0.06430685231},
{"learn":[3.139025283],"iteration":934,"passed_time":0.9106804618,"remaining_time":0.06330933692},
{"learn":[3.137824183],"iteration":935,"passed_time":0.9113161868,"remaining_time":0.0623122179},
{"learn":[3.135620453],"iteration":936,"passed_time":0.9120269177,"remaining_time":0.06132091336},
{"learn":[3.13443178],"iteration":937,"passed_time":0.9126775789,"remaining_time":0.06032623656},
{"learn":[3.132765713],"iteration":938,"passed_time":0.9132659141,"remaining_time":0.05932824362},
{"learn":[3.131434124],"iteration":939,"passed_time":0.913841575,"remaining_time":0.0583303133},
{"learn":[3.128384262],"iteration":940,"passed_time":0.9144732918,"remaining_time":0.05733679513},
{"learn":[3.128120455],"iteration":941,"passed_time":0.9151151854,"remaining_time":0.05634467171},
{"learn":[3.126314615],"iteration":942,"passed_time":0.9157231094,"remaining_time":0.05535123779},
{"learn":[3.125409666],"iteration":943,"passed_time":0.9164242206,"remaining_time":0.05436414868},
{"learn":[3.123072589],"iteration":944,"passed_time":0.917111216,"remaining_time":0.05337684326},
{"learn":[3.122921099],"iteration":945,"passed_time":0.9177180001,"remaining_time":0.05238559409},
{"learn":[3.122182662],"iteration":946,"passed_time":0.9183446363,"remaining_time":0.05139626792},
{"learn":[3.120040951],"iteration":947,"passed_time":0.9191469974,"remaining_time":0.05041734585},
{"learn":[3.118767799],"iteration":948,"passed_time":0.9202329346,"remaining_time":0.04945403547},
{"learn":[3.118203218],"iteration":949,"passed_time":0.920969015,"remaining_time":0.04847205342},
{"learn":[3.116343362],"iteration":950,"passed_time":0.9216379943,"remaining_time":0.04748713115},
{"learn":[3.11480829],"iteration":951,"passed_time":0.9222851709,"remaining_time":0.04650177332},
{"learn":[3.112607903],"iteration":952,"passed_time":0.9229446815,"remaining_time":0.04551773351},
{"learn":[3.111661241],"iteration":953,"passed_time":0.923560083,"remaining_time":0.04453224719},
{"learn":[3.110249676],"iteration":954,"passed_time":0.9242050063,"remaining_time":0.043548927},
{"learn":[3.107333579],"iteration":955,"passed_time":0.9248661133,"remaining_time":0.04256705961},
{"learn":[3.107149851],"iteration":956,"passed_time":0.9254737339,"remaining_time":0.04158345931},
{"learn":[3.106867336],"iteration":957,"passed_time":0.926112133,"remaining_time":0.04060199331},
{"learn":[3.10364681],"iteration":958,"passed_time":0.926787957,"remaining_time":0.03962284279},
{"learn":[3.102703811],"iteration":959,"passed_time":0.9275104032,"remaining_time":0.0386462668},
{"learn":[3.101469264],"iteration":960,"passed_time":0.9280781885,"remaining_time":0.03766394314},
{"learn":[3.09863569],"iteration":961,"passed_time":0.9287394413,"remaining_time":0.03668617336},
{"learn":[3.09645939],"iteration":962,"passed_time":0.9294020065,"remaining_time":0.03570911136},
{"learn":[3.096240186],"iteration":963,"passed_time":0.9299983638,"remaining_time":0.03473022935},
{"learn":[3.094838828],"iteration":964,"passed_time":0.9307279261,"remaining_time":0.03375697141},
{"learn":[3.094176802],"iteration":965,"passed_time":0.9313688272,"remaining_time":0.03278109744},
{"learn":[3.093182279],"iteration":966,"passed_time":0.9319823819,"remaining_time":0.03180498304},
{"learn":[3.090150687],"iteration":967,"passed_time":0.9326148163,"remaining_time":0.03083024186},
{"learn":[3.088612829],"iteration":968,"passed_time":0.933301805,"remaining_time":0.02985795248},
{"learn":[3.087153684],"iteration":969,"passed_time":0.9339658255,"remaining_time":0.02888554099},
{"learn":[3.085866843],"iteration":970,"passed_time":0.9349595299,"remaining_time":0.02792361109},
{"learn":[3.082669094],"iteration":971,"passed_time":0.9358264743,"remaining_time":0.02695796428},
{"learn":[3.081047548],"iteration":972,"passed_time":0.9365494562,"remaining_time":0.02598852551},
{"learn":[3.079684322],"iteration":973,"passed_time":0.9372085144,"remaining_time":0.02501788642},
{"learn":[3.07613431],"iteration":974,"passed_time":0.9378540325,"remaining_time":0.0240475393},
{"learn":[3.074005935],"iteration":975,"passed_time":0.9385342189,"remaining_time":0.0230787103},
{"learn":[3.072988853],"iteration":976,"passed_time":0.9392216087,"remaining_time":0.02211064176},
{"learn":[3.072344268],"iteration":977,"passed_time":0.9398933118,"remaining_time":0.02114279434},
{"learn":[3.070654438],"iteration":978,"passed_time":0.9406090539,"remaining_time":0.02017649656},
{"learn":[3.069724506],"iteration":979,"passed_time":0.9412971439,"remaining_time":0.01921014579},
{"learn":[3.067763166],"iteration":980,"passed_time":0.9419657301,"remaining_time":0.01824398458},
{"learn":[3.066737893],"iteration":981,"passed_time":0.9425971364,"remaining_time":0.01727774792},
{"learn":[3.065248174],"iteration":982,"passed_time":0.9432392974,"remaining_time":0.01631237849},
{"learn":[3.063186837],"iteration":983,"passed_time":0.9438950851,"remaining_time":0.01534788756},
{"learn":[3.062880371],"iteration":984,"passed_time":0.9446320197,"remaining_time":0.01438525918},
{"learn":[3.061288645],"iteration":985,"passed_time":0.9454996091,"remaining_time":0.01342494374},
{"learn":[3.059970575],"iteration":986,"passed_time":0.9463600566,"remaining_time":0.01246472212},
{"learn":[3.059576341],"iteration":987,"passed_time":0.9470450181,"remaining_time":0.01150257107},
{"learn":[3.058175919],"iteration":988,"passed_time":0.9476950849,"remaining_time":0.01054059245},
{"learn":[3.056830702],"iteration":989,"passed_time":0.9483371312,"remaining_time":0.009579162942},
{"learn":[3.056336579],"iteration":990,"passed_time":0.9490507669,"remaining_time":0.008619028156},
{"learn":[3.055810414],"iteration":991,"passed_time":0.9503407568,"remaining_time":0.007664038361},
{"learn":[3.055476518],"iteration":992,"passed_time":0.9510356265,"remaining_time":0.006704178636},
{"learn":[3.053331734],"iteration":993,"passed_time":0.951685894,"remaining_time":0.005744582861},
{"learn":[3.050890374],"iteration":994,"passed_time":0.9523816971,"remaining_time":0.004785837674},
{"learn":[3.04972623],"iteration":995,"passed_time":0.9530218519,"remaining_time":0.003827396996},
{"learn":[3.047217327],"iteration":996,"passed_time":0.9537116195,"remaining_time":0.002869744091},
{"learn":[3.047155483],"iteration":997,"passed_time":0.9543798368,"remaining_time":0.001912584843},
{"learn":[3.04430671],"iteration":998,"passed_time":0.9550802416,"remaining_time":0.0009560362778},
{"learn":[3.042664195],"iteration":999,"passed_time":0.9557077503,"remaining_time":0}
]}